<ISNIAssigned><isniUnformatted>000000012117952X</isniUnformatted><isniURI>https://isni.org/isni/000000012117952X</isniURI><dataConfidence>99</dataConfidence><personalName><forename>Eugene Victor</forename><surname>Thaw</surname><nameUse>public</nameUse><source>LCNACO</source></personalName><personalName><forename>Eugene Victor</forename><surname>Thaw</surname><source>NLN</source></personalName><personalName><forename>Eugene Victor</forename><surname>Thaw</surname><marcDate>1927-...</marcDate><nameUse>public</nameUse><source>BNF</source><subsourceIdentifier>12187829</subsourceIdentifier></personalName><personalName><forename>Eugene Victor</forename><surname>Thaw</surname><nameUse>public</nameUse><source>NTA</source></personalName><personalName><forename>Eugene Victor</forename><surname>Thaw</surname><nameUse>public</nameUse><source>VIAF</source><source>SUDOC</source><subsourceIdentifier>03046966X</subsourceIdentifier></personalName><personalName><forename>Eugene Victor</forename><surname>Thaw</surname><nameUse>public</nameUse><source>VIAF</source><source>LAC</source><subsourceIdentifier>1008E0193</subsourceIdentifier></personalName><personalName><forename>Eugene Victor</forename><surname>Thaw</surname><marcDate>1927-</marcDate><nameUse>public</nameUse><source>VIAF</source><source>NLP</source><subsourceIdentifier>a32435824</subsourceIdentifier></personalName><personalName><forename>Eugene Victor</forename><surname>Thaw</surname><marcDate>1927-</marcDate><nameUse>public</nameUse><source>VIAF</source><source>DNB</source><subsourceIdentifier>11927079X</subsourceIdentifier></personalName><personalName><forename>Eugene Victor</forename><surname>Thaw</surname><nameUse>public</nameUse><source>VIAF</source><source>JPG</source><subsourceIdentifier>500285879</subsourceIdentifier></personalName><personalName><forename>Eugene Victor</forename><surname>Thaw</surname><nameTitle>Mrs</nameTitle><source>ISNI</source></personalName><creativeActivity><creationRole source="LCNACO">aut</creationRole><creationRole source="NLN">cre</creationRole><creationClass source="LCNACO">am</creationClass><creationClass source="NLN">am</creationClass><creationClass source="BNF">am</creationClass><creationClass source="NTA">am</creationClass><creationClass source="VIAF" subsource="SUDOC">am</creationClass><titleOfWork source="LCNACO"><title>@From Mantegna to Picasso</title></titleOfWork><titleOfWork source="LCNACO"><title>@Reflections of an independent mind</title></titleOfWork><titleOfWork source="BNF"><title>@Drawings from the collection of Mr. &#38; Mrs. Eugene V. Thaw</title><subtitle>catalogue.</subtitle></titleOfWork><titleOfWork source="BNF"><title>@Jackson Pollock a catalogue raisonné of paintings, drawings and other works</title></titleOfWork><titleOfWork source="BNF"><title>@Thaw collection Master drawings and oil sketches, acquisitions since 1994 [exhibition at the Pierpont Morgan library, 27 September 2002-19 January 2003</title></titleOfWork><titleOfWork source="NTA"><title>The @abstract expressionists</title></titleOfWork><titleOfWork source="NTA"><title>@Drawings from the collection of Mr. &#38; Mrs. Eugene V. Thaw</title><subtitle>catalogue.</subtitle></titleOfWork><titleOfWork source="VIAF" subsource="SUDOC"><title>@Drawings from the collection of Mr. &#38; Mrs. Eugene V. Thaw</title><subtitle>catalogue.</subtitle></titleOfWork><titleOfWork source="VIAF" subsource="SUDOC"><title>@From Mantegna to Picasso, c1996:</title></titleOfWork><titleOfWork source="NTA"><title>@Jackson Pollock a catalogue raisonné of paintings, drawings and other works</title></titleOfWork><titleOfWork source="VIAF" subsource="SUDOC"><title>@Jackson Pollock a catalogue raisonné of paintings, drawings and other works</title></titleOfWork><titleOfWork source="VIAF" subsource="NLP"><title>@Jackson Pollock</title><statementOfResponsibility>ed. by Francis Valentine O'Connor and Eugene Victor Thaw. - Vol. 1-4. - New Haven, 1978.</statementOfResponsibility></titleOfWork><titleOfWork source="VIAF" subsource="SUDOC"><title>The @responsive eye Ralph T. Coe and the collecting of American Indian art</title><subtitle>[Catalog of an exhibition held at and org. by the Metropolitan Museum of Art, New York, Sept. 9-Dec. 14, 2003]</subtitle></titleOfWork><titleOfWork source="NTA"><title>@Spirit beings and sun dancers</title><subtitle>Black Hawk's vision of the Lakota world</subtitle></titleOfWork><titleOfWork source="VIAF" subsource="SUDOC"><title>@Spirit beings and sun dancers</title><subtitle>Black Hawk's vision of the Lakota world</subtitle></titleOfWork><identifier><identifierType>ISBN</identifierType><identifierValue>9780875980522</identifierValue><source>BNF</source></identifier><identifier><identifierType>ISBN</identifierType><identifierValue>9780300021097</identifierValue><source>BNF</source></identifier><identifier><identifierType>ISBN</identifierType><identifierValue>9780875981376</identifierValue><source>BNF</source></identifier><identifier><identifierType>ISBN</identifierType><identifierValue>9780875980522</identifierValue><source>NTA</source></identifier><identifier><identifierType>ISBN</identifierType><identifierValue>9780875980522</identifierValue><source>VIAF</source><source>SUDOC</source></identifier><identifier><identifierType>ISBN</identifierType><identifierValue>9780300021097</identifierValue><source>NTA</source></identifier><identifier><identifierType>ISBN</identifierType><identifierValue>9780300021097</identifierValue><source>VIAF</source><source>SUDOC</source></identifier><identifier><identifierType>ISBN</identifierType><identifierValue>9780875981161</identifierValue><source>VIAF</source><source>SUDOC</source></identifier><identifier><identifierType>ISBN</identifierType><identifierValue>9780875980829</identifierValue><source>NTA</source></identifier><identifier><identifierType>ISBN</identifierType><identifierValue>9780875980829</identifierValue><source>VIAF</source><source>SUDOC</source></identifier><identifier><identifierType>ISBN</identifierType><identifierValue>9780807614655</identifierValue><source>NTA</source></identifier><identifier><identifierType>ISBN</identifierType><identifierValue>9780807614655</identifierValue><source>VIAF</source><source>SUDOC</source></identifier><identifier><identifierType>ISBN</identifierType><identifierValue>9781588390868</identifierValue><source>VIAF</source><source>SUDOC</source></identifier><identifier><identifierType>ISBN</identifierType><identifierValue>9781588390851</identifierValue><source>VIAF</source><source>SUDOC</source></identifier><identifier><identifierType>ISBN</identifierType><identifierValue>9780900946516</identifierValue><source>VIAF</source><source>SUDOC</source></identifier></creativeActivity><personalNameVariant><forename>Eugene V</forename><surname>Thaw</surname><nameUse>public</nameUse><source>LCNACO</source></personalNameVariant><personalNameVariant><forename>Eugene V.</forename><surname>Thaw</surname><marcDate>1927-...</marcDate><source>BNF</source></personalNameVariant><personalNameVariant><surname>Eugene Victor Thaw</surname><source>VIAF</source><source>JPG</source></personalNameVariant><personalNameVariant><forename>Eugene</forename><surname>Thaw</surname><source>NTA</source></personalNameVariant><personalNameVariant><forename>Eugene V.</forename><surname>Thaw</surname><source>NTA</source></personalNameVariant><personalNameVariant><forename>Eugene V.</forename><surname>Thaw</surname><source>VIAF</source><source>SUDOC</source></personalNameVariant><personalNameVariant><forename>Eugene V.</forename><surname>Thaw</surname><source>VIAF</source><source>JPG</source></personalNameVariant><personalNameVariant><forename>Eugene V.</forename><surname>Thaw</surname><source>VIAF</source><source>LAC</source></personalNameVariant><personalNameVariant><forename>Eugene V.</forename><surname>Thaw</surname><marcDate>1927-</marcDate><source>VIAF</source><source>DNB</source></personalNameVariant><personalNameVariant><forename>Gene</forename><surname>Thaw</surname><marcDate>1927-</marcDate><source>VIAF</source><source>DNB</source></personalNameVariant><sources><codeOfSource>ISNI</codeOfSource><sourceIdentifier>VIAF 19558261</sourceIdentifier></sources><sources><codeOfSource>VIAF</codeOfSource><sourceIdentifier>2516598</sourceIdentifier><reference><class>ALL</class><role>CRE</role><URI>http://viaf.org/viaf/2516598</URI></reference></sources><sources><codeOfSource>BNF</codeOfSource><sourceIdentifier>12187829</sourceIdentifier></sources><sources><codeOfSource>NTA</codeOfSource><sourceIdentifier>07447720X</sourceIdentifier></sources><sources><codeOfSource>NLN</codeOfSource><sourceIdentifier>14059390</sourceIdentifier></sources><sources><codeOfSource>LCNACO</codeOfSource><sourceIdentifier>n  86024890</sourceIdentifier></sources></ISNIAssigned>