<ISNIAssigned><isniUnformatted>000000050170543X</isniUnformatted><isniURI>https://isni.org/isni/000000050170543X</isniURI><dataConfidence>60</dataConfidence><personalName><forename>Charity</forename><surname>Butcher</surname><marcDate>1976-</marcDate><nameUse>public</nameUse><source>LCNACO</source></personalName><creativeActivity><creationRole source="LCNACO">aut</creationRole><creationClass source="LCNACO">am</creationClass><titleOfWork source="LCNACO"><title>The @handbook of cross-border ethnic and religious affinities</title></titleOfWork></creativeActivity><sources><codeOfSource>LCNACO</codeOfSource><sourceIdentifier>n 2018065577</sourceIdentifier></sources></ISNIAssigned>