<ISNIAssigned><isniUnformatted>0000000121271967</isniUnformatted><isniURI>https://isni.org/isni/0000000121271967</isniURI><dataConfidence>60</dataConfidence><personalName><forename>Marcus Fabius</forename><surname>Quintilianus</surname><source>NLN</source></personalName><personalName><forename>Marcus Fabius</forename><surname>Quintilianus</surname><nameUse>public</nameUse><source>NLFIN</source></personalName><personalName><surname>Quintilien</surname><source>BAnQ</source></personalName><personalName><surname>Marcus Fabius Quintilianus</surname><nameUse>public</nameUse><source>VIAF</source><source>WKP</source><subsourceIdentifier>Q193769</subsourceIdentifier></personalName><personalName><surname>Quintilian</surname><nameUse>public</nameUse><source>LCNACO</source></personalName><personalName><surname>Quintilian</surname><nameUse>public</nameUse><source>VIAF</source><source>NLI</source><subsourceIdentifier>000108742</subsourceIdentifier></personalName><personalName><surname>Quintilian</surname><nameUse>public</nameUse><source>VIAF</source><source>PERSEUS</source><subsourceIdentifier>urn:cite:perseus:author.1209.1</subsourceIdentifier></personalName><personalName><surname>Quintilian</surname><nameUse>public</nameUse><source>VIAF</source><source>N6I</source><subsourceIdentifier>vtls000086349</subsourceIdentifier></personalName><personalName><forename>Marco Fabio</forename><surname>Quintiliano</surname><nameUse>public</nameUse><source>VIAF</source><source>BNE</source><subsourceIdentifier>XX1042668</subsourceIdentifier></personalName><personalName><surname>Quintiliano</surname><marcDate>ca 40-ca 96</marcDate><nameUse>public</nameUse><source>VIAF</source><source>PTBNP</source><subsourceIdentifier>77596</subsourceIdentifier></personalName><personalName><forename>Marcus Fabius</forename><surname>Quintilianus</surname><nameUse>public</nameUse><source>VIAF</source><source>ICCU</source><subsourceIdentifier>CFIV037714</subsourceIdentifier></personalName><personalName><forename>Marcus Fabius</forename><surname>Quintilianus</surname><nameUse>public</nameUse><source>VIAF</source><source>NDL</source><subsourceIdentifier>00453523</subsourceIdentifier></personalName><personalName><forename>Marcus Fabius</forename><surname>Quintilianus</surname><nameUse>public</nameUse><source>VIAF</source><source>NSK</source><subsourceIdentifier>000183490</subsourceIdentifier></personalName><personalName><forename>Marcus Fabius</forename><surname>Quintilianus</surname><nameUse>public</nameUse><source>VIAF</source><source>RERO</source><subsourceIdentifier>vtls000134857</subsourceIdentifier></personalName><personalName><forename>Marcus Fabius</forename><surname>Quintilianus</surname><marcDate>ca 35-95</marcDate><nameUse>public</nameUse><source>VIAF</source><source>NLP</source><subsourceIdentifier>a11429823</subsourceIdentifier></personalName><personalName><forename>Marcus Fabius</forename><surname>Quintilianus</surname><marcDate>ca 35-95</marcDate><nameUse>public</nameUse><source>VIAF</source><source>NUKAT</source><subsourceIdentifier>n  96401169</subsourceIdentifier></personalName><personalName><forename>Marcus Fabius</forename><surname>Quintilianus</surname><marcDate>35-100</marcDate><nameUse>public</nameUse><source>VIAF</source><source>DNB</source><subsourceIdentifier>118597396</subsourceIdentifier></personalName><personalName><forename>Marcus Fabius</forename><surname>Quintilianus</surname><marcDate>asi 35-asi 100</marcDate><nameUse>public</nameUse><source>VIAF</source><source>NKC</source><subsourceIdentifier>jn19981002067</subsourceIdentifier></personalName><personalName><forename>Marcus Fabius</forename><surname>Quintilianus</surname><marcDate>c. 35-c. 96</marcDate><nameUse>public</nameUse><source>VIAF</source><source>BAV</source><subsourceIdentifier>ADV10048786</subsourceIdentifier></personalName><personalName><surname>Quintilianus</surname><marcDate>ca 35-ca 100</marcDate><nameUse>public</nameUse><source>NLS</source></personalName><personalName><surname>Quintilien</surname><nameUse>public</nameUse><source>VIAF</source><source>B2Q</source><subsourceIdentifier>0000948706</subsourceIdentifier></personalName><personalName><surname>Quintilien</surname><marcDate>0030?-0100?</marcDate><nameUse>public</nameUse><source>VIAF</source><source>SUDOC</source><subsourceIdentifier>026668580</subsourceIdentifier></personalName><personalName><forename>Marc Fabi</forename><surname>Quintilià</surname><marcDate>ca. 30-ca. 95</marcDate><nameUse>public</nameUse><source>VIAF</source><source>BNC</source><subsourceIdentifier>a10475515</subsourceIdentifier></personalName><personalName><forename>Marcus Fabius</forename><surname>Quintilianus</surname><marcDate>ca35-96</marcDate><nameUse>public</nameUse><source>NTA</source></personalName><personalName><surname>Quintilien</surname><marcDate>0030?-0100?</marcDate><nameUse>public</nameUse><source>BNF</source><subsourceIdentifier>11887333</subsourceIdentifier></personalName><personalName><forename>Marcus Fabius</forename><surname>Quintilianus</surname><source>OCLCT</source><subsourceIdentifier>250876124</subsourceIdentifier></personalName><creativeActivity><creationRole source="NLN">cre</creationRole><creationRole source="NLFIN">aut</creationRole><creationRole source="BAnQ">cre</creationRole><creationRole source="VIAF" subsource="NKC">aut</creationRole><creationRole source="NTA">aut</creationRole><creationRole source="OCLCT">aut</creationRole><creationClass source="NLN">am</creationClass><creationClass source="NLFIN">am</creationClass><creationClass source="BAnQ">as</creationClass><creationClass source="VIAF" subsource="NKC">am</creationClass><creationClass source="VIAF" subsource="NLI">am</creationClass><creationClass source="VIAF" subsource="NUKAT">am</creationClass><creationClass source="VIAF" subsource="B2Q">am</creationClass><creationClass source="VIAF" subsource="BAV">am</creationClass><creationClass source="VIAF" subsource="DNB">am</creationClass><creationClass source="NLS">am</creationClass><creationClass source="VIAF" subsource="SUDOC">am</creationClass><creationClass source="VIAF" subsource="BNE">am</creationClass><creationClass source="VIAF" subsource="N6I">am</creationClass><creationClass source="VIAF" subsource="NDL">am</creationClass><creationClass source="VIAF" subsource="NLP">am</creationClass><creationClass source="VIAF" subsource="NSK">am</creationClass><creationClass source="VIAF" subsource="RERO">am</creationClass><creationClass source="VIAF" subsource="PTBNP">am</creationClass><creationClass source="VIAF" subsource="BNC">am</creationClass><creationClass source="VIAF" subsource="SUDOC">im</creationClass><creationClass source="VIAF" subsource="SUDOC">mm</creationClass><creationClass source="VIAF" subsource="BNE">tm</creationClass><creationClass source="NTA">am</creationClass><creationClass source="NTA">ta</creationClass><creationClass source="NTA">tm</creationClass><creationClass source="BNF">am</creationClass><creationClass source="BNF">im</creationClass><titleOfWork source="NLFIN"><title>@Institutio oratoria</title></titleOfWork><titleOfWork source="NLFIN"><title>@Institutionis oratoriae lib. X</title></titleOfWork><titleOfWork source="NLFIN"><title>@Institutionis oratoriae liber III</title></titleOfWork><titleOfWork source="NLFIN"><title>@M. Fabi Quintiliani Institutionis oratoriae libri XII</title></titleOfWork><titleOfWork source="NLFIN"><title>@M. Fabij Quintiliani Institutionum oratoriarum libri duodecim summa diligentia ad fidem vetustissimorum codicum recogniti, ac restituti. Cum ... indice locupletissimo. Declamationum liber eiusdem</title></titleOfWork><titleOfWork source="NLFIN"><title>@Quintilian on the teaching of speaking and writing</title><subtitle>translations from books one, two, and ten of the Institutio oratoria</subtitle></titleOfWork><titleOfWork source="NLFIN"><title>@Van't onthouden uyt Fabius Quintilianus van de spreekkunstelijke onderwijsning</title></titleOfWork><titleOfWork source="NLFIN"><title>@Zwölf Bücher Anleitung zur Beredtsamkeit</title></titleOfWork><titleOfWork source="NLFIN"><title>De @institutione oratoria libri XII</title></titleOfWork><titleOfWork source="NLFIN"><title>De @l'institution de l'orateur</title></titleOfWork><titleOfWork source="VIAF" subsource="DNB"><title>@Amici vades</title></titleOfWork><titleOfWork source="VIAF" subsource="DNB"><title>@Apes pauperis</title></titleOfWork><titleOfWork source="VIAF" subsource="NUKAT"><title>@Ausbildung des redners</title><subtitle>Zwölf bücher.</subtitle></titleOfWork><titleOfWork source="VIAF" subsource="RERO"><title>@Ausbildung des redners</title><subtitle>Zwölf bücher.</subtitle></titleOfWork><titleOfWork source="VIAF" subsource="DNB"><title>@Ausbildung des redners</title><subtitle>Zwölf bücher.</subtitle></titleOfWork><titleOfWork source="VIAF" subsource="BNC"><title>@Ausbildung des redners</title><subtitle>Zwölf bücher.</subtitle></titleOfWork><titleOfWork source="VIAF" subsource="NDL"><title>@Benronka no kyōiku.</title></titleOfWork><titleOfWork source="VIAF" subsource="DNB"><title>@Cadaveribus pasti</title></titleOfWork><titleOfWork source="LCNACO"><title>De @causis corruptae eloquentiae</title></titleOfWork><titleOfWork source="VIAF" subsource="WKP"><title>De @causis corruptae eloquentiae</title></titleOfWork><titleOfWork source="NLS"><title>@Cornelius Nepos, Eutropius, Quintrilianus</title></titleOfWork><titleOfWork source="VIAF" subsource="DNB"><title>@Corporis proiecti</title></titleOfWork><titleOfWork source="VIAF" subsource="NLP"><title>@Declamationes</title></titleOfWork><titleOfWork source="VIAF" subsource="NUKAT"><title>@Declamationes</title></titleOfWork><titleOfWork source="LCNACO"><title>@Declamationes</title></titleOfWork><titleOfWork source="VIAF" subsource="BAV"><title>@Declamationes</title></titleOfWork><titleOfWork source="VIAF" subsource="DNB"><title>@Declamationes</title></titleOfWork><titleOfWork source="VIAF" subsource="PTBNP"><title>@Declamationes</title></titleOfWork><titleOfWork source="VIAF" subsource="RERO"><title>@Declamationes</title></titleOfWork><titleOfWork source="VIAF" subsource="SUDOC"><title>@Declamationes</title></titleOfWork><titleOfWork source="VIAF" subsource="BNC"><title>@Declamationes</title></titleOfWork><titleOfWork source="VIAF" subsource="SUDOC"><title>@Declamationes maiores</title></titleOfWork><titleOfWork source="VIAF" subsource="DNB"><title>@Declamationes maiores</title></titleOfWork><titleOfWork source="VIAF" subsource="DNB"><title>@Declamationes maiores 18-19</title></titleOfWork><titleOfWork source="VIAF" subsource="DNB"><title>@Declamationes minores</title></titleOfWork><titleOfWork source="VIAF" subsource="SUDOC"><title>@Declamationes minores</title></titleOfWork><titleOfWork source="LCNACO"><title>@Declamationes minores</title></titleOfWork><titleOfWork source="VIAF" subsource="DNB"><title>@Declamationes minores 317</title></titleOfWork><titleOfWork source="VIAF" subsource="NLP"><title>@Declamationes pseudo-Quintilianeae (Maiores)</title></titleOfWork><titleOfWork source="VIAF" subsource="N6I"><title>@Declamationes pseudo-Quintilianeae (Maiores)</title></titleOfWork><titleOfWork source="VIAF" subsource="NUKAT"><title>@Declamationes pseudo-Quintilianeae (Maiores)</title></titleOfWork><titleOfWork source="LCNACO"><title>@Declamationes pseudo-Quintilianeae (Maiores)</title></titleOfWork><titleOfWork source="VIAF" subsource="DNB"><title>@Declamationes pseudo-Quintilianeae (Maiores)</title></titleOfWork><titleOfWork source="VIAF" subsource="BAV"><title>@Declamationes pseudo-Quintilianeae (Maiores)</title></titleOfWork><titleOfWork source="VIAF" subsource="SUDOC"><title>@Declamationes pseudo-Quintilianeae (Maiores)</title></titleOfWork><titleOfWork source="VIAF" subsource="BNE"><title>@Declamationes pseudo-Quintilianeae (Maiores)</title></titleOfWork><titleOfWork source="NLS"><title>@Declamationes pseudo-Quintilianeae (Maiores)</title></titleOfWork><titleOfWork source="VIAF" subsource="RERO"><title>@Declamationes pseudo-Quintilianeae (Maiores)</title></titleOfWork><titleOfWork source="VIAF" subsource="PTBNP"><title>@Declamationes pseudo-Quintilianeae (Maiores)</title></titleOfWork><titleOfWork source="VIAF" subsource="BNC"><title>@Declamationes pseudo-Quintilianeae (Maiores)</title></titleOfWork><titleOfWork source="LCNACO"><title>@Declamationes pseudo-Quintilianeae (Maiores).</title></titleOfWork><titleOfWork source="VIAF" subsource="DNB"><title>@Dives accusatus proditionis</title></titleOfWork><titleOfWork source="VIAF" subsource="DNB"><title>@Gemini languentes</title></titleOfWork><titleOfWork source="VIAF" subsource="DNB"><title>@Gladiator</title></titleOfWork><titleOfWork source="VIAF" subsource="DNB"><title>@Institutio oratoria 1,4-8</title></titleOfWork><titleOfWork source="VIAF" subsource="DNB"><title>@Institutio oratoria 10</title></titleOfWork><titleOfWork source="VIAF" subsource="NLI"><title>@Institutio oratoria 10,1,46-131</title></titleOfWork><titleOfWork source="VIAF" subsource="NUKAT"><title>@Institutio oratoria 10,1,46-131</title></titleOfWork><titleOfWork source="VIAF" subsource="B2Q"><title>@Institutio oratoria 10,1,46-131</title></titleOfWork><titleOfWork source="NLS"><title>@Institutio oratoria 10,1,46-131</title></titleOfWork><titleOfWork source="LCNACO"><title>@Institutio oratoria 10,1,46-131</title></titleOfWork><titleOfWork source="VIAF" subsource="BNE"><title>@Institutio oratoria 10,1,46-131</title></titleOfWork><titleOfWork source="VIAF" subsource="NSK"><title>@Institutio oratoria 10,1,46-131</title></titleOfWork><titleOfWork source="VIAF" subsource="PTBNP"><title>@Institutio oratoria 10,1,46-131</title></titleOfWork><titleOfWork source="VIAF" subsource="SUDOC"><title>@Institutio oratoria 10,1,46-131</title></titleOfWork><titleOfWork source="VIAF" subsource="BNC"><title>@Institutio oratoria 10,1,46-131</title></titleOfWork><titleOfWork source="VIAF" subsource="NKC"><title>@Institutio oratoria 10,1,46-131</title></titleOfWork><titleOfWork source="VIAF" subsource="BAV"><title>@Institutio oratoria 10,1,46-131</title></titleOfWork><titleOfWork source="VIAF" subsource="DNB"><title>@Institutio oratoria 10,1,46-131</title></titleOfWork><titleOfWork source="VIAF" subsource="N6I"><title>@Institutio oratoria 10,1,46-131</title></titleOfWork><titleOfWork source="VIAF" subsource="NLP"><title>@Institutio oratoria 10,1,46-131</title></titleOfWork><titleOfWork source="VIAF" subsource="RERO"><title>@Institutio oratoria 10,1,46-131</title></titleOfWork><titleOfWork source="VIAF" subsource="DNB"><title>@Institutio oratoria 11,3,84-124</title></titleOfWork><titleOfWork source="VIAF" subsource="DNB"><title>@Institutio oratoria 12</title></titleOfWork><titleOfWork source="VIAF" subsource="DNB"><title>@Institutio oratoria 2</title></titleOfWork><titleOfWork source="VIAF" subsource="DNB"><title>@Institutio oratoria 3</title></titleOfWork><titleOfWork source="VIAF" subsource="DNB"><title>@Institutio oratoria 6,3</title></titleOfWork><titleOfWork source="VIAF" subsource="DNB"><title>@Institutio oratoria 8</title></titleOfWork><titleOfWork source="VIAF" subsource="BNE"><title>@Institutio oratoria 8</title></titleOfWork><titleOfWork source="VIAF" subsource="BNC"><title>@Institutio oratoria 8</title></titleOfWork><titleOfWork source="VIAF" subsource="NUKAT"><title>@Institutio oratoria 8</title></titleOfWork><titleOfWork source="VIAF" subsource="DNB"><title>@Institutio oratoria Lib. 10</title></titleOfWork><titleOfWork source="VIAF" subsource="BNE"><title>@Institutio oratoria. Liber 3</title></titleOfWork><titleOfWork source="VIAF" subsource="DNB"><title>@Institutio oratoria Praefatio 8</title></titleOfWork><titleOfWork source="LCNACO"><title>@Institutiones oratoriae</title></titleOfWork><titleOfWork source="VIAF" subsource="DNB"><title>@Institutiones oratoriae</title></titleOfWork><titleOfWork source="VIAF" subsource="B2Q"><title>@Institutiones oratoriae</title></titleOfWork><titleOfWork source="VIAF" subsource="BNE"><title>@Institutiones oratoriae</title></titleOfWork><titleOfWork source="VIAF" subsource="NLI"><title>@Institutiones oratoriae</title></titleOfWork><titleOfWork source="VIAF" subsource="N6I"><title>@Institutiones oratoriae</title></titleOfWork><titleOfWork source="LCNACO"><title>@Institutiones oratoriae. Liber 10. Caput 1</title></titleOfWork><titleOfWork source="VIAF" subsource="NKC"><title>@Institutiones oratoriae. Liber 2</title></titleOfWork><titleOfWork source="VIAF" subsource="NUKAT"><title>@Institutiones oratoriae. Liber 2</title></titleOfWork><titleOfWork source="NLS"><title>@Institutiones oratoriae. Liber 2</title></titleOfWork><titleOfWork source="LCNACO"><title>@Institutiones oratoriae. Liber 2</title></titleOfWork><titleOfWork source="VIAF" subsource="BNE"><title>@Institutiones oratoriae. Liber 2</title></titleOfWork><titleOfWork source="VIAF" subsource="SUDOC"><title>@Institutiones oratoriae. Liber 2</title></titleOfWork><titleOfWork source="VIAF" subsource="NLI"><title>@Institutiones oratoriae. Liber 2</title></titleOfWork><titleOfWork source="VIAF" subsource="PTBNP"><title>@Institutiones oratoriae. Liber 2</title></titleOfWork><titleOfWork source="VIAF" subsource="NLP"><title>@Institutiones oratoriae. Liber 2</title></titleOfWork><titleOfWork source="VIAF" subsource="BNC"><title>@Institutiones oratoriae. Liber 2</title></titleOfWork><titleOfWork source="VIAF" subsource="BAV"><title>@Institutiones oratoriae. Liber 2</title></titleOfWork><titleOfWork source="VIAF" subsource="DNB"><title>@Institutiones oratoriae. Liber 2</title></titleOfWork><titleOfWork source="VIAF" subsource="PERSEUS"><title>@Institutiones oratoriae. Liber 2</title></titleOfWork><titleOfWork source="VIAF" subsource="N6I"><title>@Institutiones oratoriae. Liber 2</title></titleOfWork><titleOfWork source="VIAF" subsource="NDL"><title>@Institutiones oratoriae. Liber 2</title></titleOfWork><titleOfWork source="VIAF" subsource="RERO"><title>@Institutiones oratoriae. Liber 2</title></titleOfWork><titleOfWork source="LCNACO"><title>@Institutiones oratoriae. Selections</title></titleOfWork><titleOfWork source="VIAF" subsource="NLP"><title>@Kształcenie mówcy</title><subtitle>ksiegi I, II, X</subtitle></titleOfWork><titleOfWork source="VIAF" subsource="NUKAT"><title>@Kształcenie mówcy</title><subtitle>ksiegi I, II, X</subtitle></titleOfWork><titleOfWork source="VIAF" subsource="BNE"><title>@Kształcenie mówcy</title><subtitle>ksiegi I, II, X</subtitle></titleOfWork><titleOfWork source="VIAF" subsource="BNC"><title>@Kształcenie mówcy</title><subtitle>ksiegi I, II, X</subtitle></titleOfWork><titleOfWork source="VIAF" subsource="NUKAT"><title>De @l'institution oratoire</title></titleOfWork><titleOfWork source="VIAF" subsource="BAV"><title>De @l'institution oratoire</title></titleOfWork><titleOfWork source="VIAF" subsource="SUDOC"><title>De @l'institution oratoire</title></titleOfWork><titleOfWork source="VIAF" subsource="RERO"><title>De @l'institution oratoire</title></titleOfWork><titleOfWork source="VIAF" subsource="DNB"><title>@Marci Fabii Quinctiliani Opera</title></titleOfWork><titleOfWork source="VIAF" subsource="DNB"><title>@Mathematicus</title></titleOfWork><titleOfWork source="LCNACO"><title>@Mathematicus</title></titleOfWork><titleOfWork source="VIAF" subsource="DNB"><title>@Miles marianus</title></titleOfWork><titleOfWork source="LCNACO"><title>@Miles marianus</title></titleOfWork><titleOfWork source="VIAF" subsource="SUDOC"><title>@Miles marianus</title></titleOfWork><titleOfWork source="VIAF" subsource="DNB"><title>@Odii potio 1</title></titleOfWork><titleOfWork source="VIAF" subsource="DNB"><title>@Odii potio 2</title></titleOfWork><titleOfWork source="VIAF" subsource="NLI"><title>@Oeuvres complètes</title></titleOfWork><titleOfWork source="VIAF" subsource="B2Q"><title>@Oeuvres complètes</title></titleOfWork><titleOfWork source="VIAF" subsource="PTBNP"><title>@Oeuvres complètes</title></titleOfWork><titleOfWork source="VIAF" subsource="BAV"><title>@Oeuvres complètes</title></titleOfWork><titleOfWork source="VIAF" subsource="BNE"><title>@Oeuvres complètes</title></titleOfWork><titleOfWork source="VIAF" subsource="RERO"><title>@Oeuvres complètes</title></titleOfWork><titleOfWork source="VIAF" subsource="SUDOC"><title>@Oeuvres complètes</title></titleOfWork><titleOfWork source="VIAF" subsource="BNC"><title>@Oeuvres complètes</title></titleOfWork><titleOfWork source="VIAF" subsource="BNE"><title>@[Opera omnia]</title></titleOfWork><titleOfWork source="VIAF" subsource="RERO"><title>@[Opera omnia]</title></titleOfWork><titleOfWork source="VIAF" subsource="DNB"><title>@[Opera omnia]</title></titleOfWork><titleOfWork source="VIAF" subsource="NLP"><title>The @orator's education</title></titleOfWork><titleOfWork source="VIAF" subsource="NUKAT"><title>The @orator's education</title></titleOfWork><titleOfWork source="VIAF" subsource="RERO"><title>The @orator's education</title></titleOfWork><titleOfWork source="LCNACO"><title>The @orator's education</title></titleOfWork><titleOfWork source="VIAF" subsource="NSK"><title>The @orator's education</title></titleOfWork><titleOfWork source="VIAF" subsource="BNC"><title>The @orator's education</title></titleOfWork><titleOfWork source="VIAF" subsource="SUDOC"><title>The @orator's education</title></titleOfWork><titleOfWork source="VIAF" subsource="BAV"><title>The @orator's education</title></titleOfWork><titleOfWork source="VIAF" subsource="RERO"><title>@Quintilians Grammatik (Inst. orat. 1, 4-8)</title><subtitle>Text, Übersetzung und Kommentar</subtitle></titleOfWork><titleOfWork source="VIAF" subsource="SUDOC"><title>@Quintilians Grammatik (Inst. orat. 1, 4-8)</title><subtitle>Text, Übersetzung und Kommentar</subtitle></titleOfWork><titleOfWork source="VIAF" subsource="BAV"><title>@Quintilians Grammatik (Inst. orat. 1, 4-8)</title><subtitle>Text, Übersetzung und Kommentar</subtitle></titleOfWork><titleOfWork source="LCNACO"><title>@Quintilians Grammatik (Inst. orat. 1, 4-8)</title><subtitle>Text, Übersetzung und Kommentar</subtitle></titleOfWork><titleOfWork source="VIAF" subsource="NUKAT"><title>@Quintilianus cum commento</title></titleOfWork><titleOfWork source="VIAF" subsource="ICCU"><title>@Quintilianus cum commento</title></titleOfWork><titleOfWork source="LCNACO"><title>@Quintilianus cum commento</title></titleOfWork><titleOfWork source="VIAF" subsource="BAV"><title>@Quintilianus cum commento</title></titleOfWork><titleOfWork source="VIAF" subsource="SUDOC"><title>@Quintilianus cum commento</title></titleOfWork><titleOfWork source="VIAF" subsource="PTBNP"><title>@Quintilianus cum commento</title></titleOfWork><titleOfWork source="VIAF" subsource="DNB"><title>@Sammlung</title></titleOfWork><titleOfWork source="VIAF" subsource="DNB"><title>@Sepulcrum incantatum</title></titleOfWork><titleOfWork source="VIAF" subsource="RERO"><title>@soldat de Marius</title></titleOfWork><titleOfWork source="VIAF" subsource="DNB"><title>@Venenum effusum</title></titleOfWork><titleOfWork source="VIAF" subsource="NDL"><title>@弁論家の教育.</title></titleOfWork><titleOfWork source="NTA"><title>@artes</title></titleOfWork><titleOfWork source="NTA"><title>@Declamationes</title></titleOfWork><titleOfWork source="NTA"><title>@Declamationes pseudo-Quintilianeae (Maiores)</title></titleOfWork><titleOfWork source="NTA"><title>@Dialogus de oratoribus</title></titleOfWork><titleOfWork source="NTA"><title>@Institutio oratoria 10,1,46-131</title></titleOfWork><titleOfWork source="NTA"><title>@Institutio oratoria 8</title></titleOfWork><titleOfWork source="NTA"><title>@Institutio oratoria Praefatio 8</title></titleOfWork><titleOfWork source="NTA"><title>@Institutiones oratoriae. Liber 2</title></titleOfWork><titleOfWork source="NTA"><title>De @l'institution oratoire</title></titleOfWork><titleOfWork source="NTA"><title>@Oeuvres complètes</title></titleOfWork><titleOfWork source="NTA"><title>@[Opera omnia]</title></titleOfWork><titleOfWork source="NTA"><title>The @orator's education</title></titleOfWork><titleOfWork source="NTA"><title>@soldat de Marius</title></titleOfWork><titleOfWork source="BNF"><title>@Declamationes</title></titleOfWork><titleOfWork source="BNF"><title>@Declamationes minores</title></titleOfWork><titleOfWork source="BNF"><title>@Declamationes minores</title></titleOfWork><titleOfWork source="BNF"><title>@Declamationes pseudo-Quintilianeae (Maiores).</title></titleOfWork><titleOfWork source="BNF"><title>@Institutio oratoria</title></titleOfWork><titleOfWork source="BNF"><title>@Institutio oratoria 10,1,46-131</title></titleOfWork><titleOfWork source="BNF"><title>@Institutio oratoria 8</title></titleOfWork><titleOfWork source="BNF"><title>@Institutiones oratoriae</title></titleOfWork><titleOfWork source="BNF"><title>@Institutiones oratoriae. Liber 2</title></titleOfWork><titleOfWork source="BNF"><title>@Oeuvres complètes</title></titleOfWork><titleOfWork source="BNF"><title>The @orator's education</title></titleOfWork><titleOfWork source="BNF"><title>@Quintilianus cum commento</title></titleOfWork><titleOfWork source="BNF"><title>@secret de Démosthène</title></titleOfWork><titleOfWork source="BNF"><title>@soldat de Marius</title></titleOfWork><titleOfWork source="OCLCT"><title>De @Quintiliano grammatico</title></titleOfWork><identifier><identifierType>ISBN</identifierType><identifierValue>9780809313778</identifierValue><source>NLFIN</source></identifier><identifier><identifierType>ISBN</identifierType><identifierValue>9780809313785</identifierValue><source>NLFIN</source></identifier><identifier><identifierType>ISBN</identifierType><identifierValue>9789525710243</identifierValue><source>NLFIN</source></identifier><identifier><identifierType>ISBN</identifierType><identifierValue>9783534046386</identifierValue><source>VIAF</source><source>NUKAT</source></identifier><identifier><identifierType>ISBN</identifierType><identifierValue>9783534046386</identifierValue><source>VIAF</source><source>DNB</source></identifier><identifier><identifierType>ISBN</identifierType><identifierValue>9783534046386</identifierValue><source>VIAF</source><source>RERO</source></identifier><identifier><identifierType>ISBN</identifierType><identifierValue>9783534046386</identifierValue><source>VIAF</source><source>SUDOC</source></identifier><identifier><identifierType>ISBN</identifierType><identifierValue>9783534046386</identifierValue><source>VIAF</source><source>BNC</source></identifier><identifier><identifierType>ISBN</identifierType><identifierValue>9783534046379</identifierValue><source>VIAF</source><source>NUKAT</source></identifier><identifier><identifierType>ISBN</identifierType><identifierValue>9783534046379</identifierValue><source>VIAF</source><source>DNB</source></identifier><identifier><identifierType>ISBN</identifierType><identifierValue>9783534046379</identifierValue><source>VIAF</source><source>RERO</source></identifier><identifier><identifierType>ISBN</identifierType><identifierValue>9783534046379</identifierValue><source>VIAF</source><source>SUDOC</source></identifier><identifier><identifierType>ISBN</identifierType><identifierValue>9783534046379</identifierValue><source>VIAF</source><source>BNC</source></identifier><identifier><identifierType>ISBN</identifierType><identifierValue>9783150029565</identifierValue><source>NLS</source></identifier><identifier><identifierType>ISBN</identifierType><identifierValue>9783150029565</identifierValue><source>VIAF</source><source>DNB</source></identifier><identifier><identifierType>ISBN</identifierType><identifierValue>9783150029565</identifierValue><source>VIAF</source><source>RERO</source></identifier><identifier><identifierType>ISBN</identifierType><identifierValue>9783150029565</identifierValue><source>VIAF</source><source>SUDOC</source></identifier><identifier><identifierType>ISBN</identifierType><identifierValue>9783150029565</identifierValue><source>VIAF</source><source>BNC</source></identifier><identifier><identifierType>ISBN</identifierType><identifierValue>9780674995956</identifierValue><source>VIAF</source><source>NLP</source></identifier><identifier><identifierType>ISBN</identifierType><identifierValue>9780674995956</identifierValue><source>VIAF</source><source>NUKAT</source></identifier><identifier><identifierType>ISBN</identifierType><identifierValue>9780674995956</identifierValue><source>VIAF</source><source>RERO</source></identifier><identifier><identifierType>ISBN</identifierType><identifierValue>9780674995956</identifierValue><source>LCNACO</source></identifier><identifier><identifierType>ISBN</identifierType><identifierValue>9780674995956</identifierValue><source>VIAF</source><source>BNC</source></identifier><identifier><identifierType>ISBN</identifierType><identifierValue>9780674995956</identifierValue><source>VIAF</source><source>SUDOC</source></identifier><identifier><identifierType>ISBN</identifierType><identifierValue>9780674995956</identifierValue><source>VIAF</source><source>BAV</source></identifier><identifier><identifierType>ISBN</identifierType><identifierValue>9780674995949</identifierValue><source>VIAF</source><source>NLP</source></identifier><identifier><identifierType>ISBN</identifierType><identifierValue>9780674995949</identifierValue><source>VIAF</source><source>NUKAT</source></identifier><identifier><identifierType>ISBN</identifierType><identifierValue>9780674995949</identifierValue><source>VIAF</source><source>RERO</source></identifier><identifier><identifierType>ISBN</identifierType><identifierValue>9780674995949</identifierValue><source>LCNACO</source></identifier><identifier><identifierType>ISBN</identifierType><identifierValue>9780674995949</identifierValue><source>VIAF</source><source>BNC</source></identifier><identifier><identifierType>ISBN</identifierType><identifierValue>9780674995949</identifierValue><source>VIAF</source><source>SUDOC</source></identifier><identifier><identifierType>ISBN</identifierType><identifierValue>9780674995949</identifierValue><source>VIAF</source><source>BAV</source></identifier><identifier><identifierType>ISBN</identifierType><identifierValue>9780674995932</identifierValue><source>VIAF</source><source>NLP</source></identifier><identifier><identifierType>ISBN</identifierType><identifierValue>9780674995932</identifierValue><source>VIAF</source><source>NUKAT</source></identifier><identifier><identifierType>ISBN</identifierType><identifierValue>9780674995932</identifierValue><source>VIAF</source><source>RERO</source></identifier><identifier><identifierType>ISBN</identifierType><identifierValue>9780674995932</identifierValue><source>LCNACO</source></identifier><identifier><identifierType>ISBN</identifierType><identifierValue>9780674995932</identifierValue><source>VIAF</source><source>BNC</source></identifier><identifier><identifierType>ISBN</identifierType><identifierValue>9780674995932</identifierValue><source>VIAF</source><source>SUDOC</source></identifier><identifier><identifierType>ISBN</identifierType><identifierValue>9780674995932</identifierValue><source>VIAF</source><source>BAV</source></identifier><identifier><identifierType>ISBN</identifierType><identifierValue>9780674995925</identifierValue><source>VIAF</source><source>NLP</source></identifier><identifier><identifierType>ISBN</identifierType><identifierValue>9780674995925</identifierValue><source>VIAF</source><source>NUKAT</source></identifier><identifier><identifierType>ISBN</identifierType><identifierValue>9780674995925</identifierValue><source>VIAF</source><source>RERO</source></identifier><identifier><identifierType>ISBN</identifierType><identifierValue>9780674995925</identifierValue><source>LCNACO</source></identifier><identifier><identifierType>ISBN</identifierType><identifierValue>9780674995925</identifierValue><source>VIAF</source><source>BNC</source></identifier><identifier><identifierType>ISBN</identifierType><identifierValue>9780674995925</identifierValue><source>VIAF</source><source>SUDOC</source></identifier><identifier><identifierType>ISBN</identifierType><identifierValue>9780674995925</identifierValue><source>VIAF</source><source>BAV</source></identifier><identifier><identifierType>ISBN</identifierType><identifierValue>9780674995918</identifierValue><source>VIAF</source><source>NLP</source></identifier><identifier><identifierType>ISBN</identifierType><identifierValue>9780674995918</identifierValue><source>VIAF</source><source>RERO</source></identifier><identifier><identifierType>ISBN</identifierType><identifierValue>9780674995918</identifierValue><source>LCNACO</source></identifier><identifier><identifierType>ISBN</identifierType><identifierValue>9780674995918</identifierValue><source>VIAF</source><source>BNC</source></identifier><identifier><identifierType>ISBN</identifierType><identifierValue>9780674995918</identifierValue><source>VIAF</source><source>SUDOC</source></identifier><identifier><identifierType>ISBN</identifierType><identifierValue>9780674995918</identifierValue><source>VIAF</source><source>BAV</source></identifier><identifier><identifierType>ISBN</identifierType><identifierValue>9780674991415</identifierValue><source>NLS</source></identifier><identifier><identifierType>ISBN</identifierType><identifierValue>9780674991415</identifierValue><source>VIAF</source><source>BAV</source></identifier><identifier><identifierType>ISBN</identifierType><identifierValue>9780674991415</identifierValue><source>VIAF</source><source>RERO</source></identifier><identifier><identifierType>ISBN</identifierType><identifierValue>9780674991415</identifierValue><source>VIAF</source><source>SUDOC</source></identifier><identifier><identifierType>ISBN</identifierType><identifierValue>9780674991385</identifierValue><source>NLS</source></identifier><identifier><identifierType>ISBN</identifierType><identifierValue>9780674991385</identifierValue><source>VIAF</source><source>BAV</source></identifier><identifier><identifierType>ISBN</identifierType><identifierValue>9780674991385</identifierValue><source>VIAF</source><source>RERO</source></identifier><identifier><identifierType>ISBN</identifierType><identifierValue>9780674991385</identifierValue><source>VIAF</source><source>SUDOC</source></identifier><identifier><identifierType>ISBN</identifierType><identifierValue>9783534118380</identifierValue><source>VIAF</source><source>DNB</source></identifier><identifier><identifierType>ISBN</identifierType><identifierValue>9788472253735</identifierValue><source>VIAF</source><source>BNC</source></identifier><identifier><identifierType>ISBN</identifierType><identifierValue>9784876981595</identifierValue><source>VIAF</source><source>NDL</source></identifier><identifier><identifierType>ISBN</identifierType><identifierValue>9783534200269</identifierValue><source>VIAF</source><source>NUKAT</source></identifier><identifier><identifierType>ISBN</identifierType><identifierValue>9789899880900</identifierValue><source>VIAF</source><source>PTBNP</source></identifier><identifier><identifierType>ISBN</identifierType><identifierValue>9788883170775</identifierValue><source>VIAF</source><source>BAV</source></identifier><identifier><identifierType>ISBN</identifierType><identifierValue>9788772886152</identifierValue><source>NLS</source></identifier><identifier><identifierType>ISBN</identifierType><identifierValue>9788472994447</identifierValue><source>VIAF</source><source>BNE</source></identifier><identifier><identifierType>ISBN</identifierType><identifierValue>9788388149740</identifierValue><source>VIAF</source><source>NLP</source></identifier><identifier><identifierType>ISBN</identifierType><identifierValue>9782251113111</identifierValue><source>VIAF</source><source>NKC</source></identifier><identifier><identifierType>ISBN</identifierType><identifierValue>9780198146551</identifierValue><source>VIAF</source><source>N6I</source></identifier><identifier><identifierType>ISBN</identifierType><identifierValue>9783534046386</identifierValue><source>NTA</source></identifier><identifier><identifierType>ISBN</identifierType><identifierValue>9783534046379</identifierValue><source>NTA</source></identifier><identifier><identifierType>ISBN</identifierType><identifierValue>9783150029565</identifierValue><source>NTA</source></identifier><identifier><identifierType>ISBN</identifierType><identifierValue>9780674995956</identifierValue><source>NTA</source></identifier><identifier><identifierType>ISBN</identifierType><identifierValue>9780674995949</identifierValue><source>NTA</source></identifier><identifier><identifierType>ISBN</identifierType><identifierValue>9780674995932</identifierValue><source>NTA</source></identifier><identifier><identifierType>ISBN</identifierType><identifierValue>9780674995925</identifierValue><source>NTA</source></identifier><identifier><identifierType>ISBN</identifierType><identifierValue>9780674995918</identifierValue><source>NTA</source></identifier><identifier><identifierType>ISBN</identifierType><identifierValue>9780674991415</identifierValue><source>NTA</source></identifier><identifier><identifierType>ISBN</identifierType><identifierValue>9780674991385</identifierValue><source>NTA</source></identifier><identifier><identifierType>ISBN</identifierType><identifierValue>9783534046379</identifierValue><source>BNF</source></identifier><identifier><identifierType>ISBN</identifierType><identifierValue>9783534046386</identifierValue><source>BNF</source></identifier><identifier><identifierType>ISBN</identifierType><identifierValue>9780674995956</identifierValue><source>BNF</source></identifier><identifier><identifierType>ISBN</identifierType><identifierValue>9780674995949</identifierValue><source>BNF</source></identifier><identifier><identifierType>ISBN</identifierType><identifierValue>9780674995932</identifierValue><source>BNF</source></identifier><identifier><identifierType>ISBN</identifierType><identifierValue>9780674995925</identifierValue><source>BNF</source></identifier><identifier><identifierType>ISBN</identifierType><identifierValue>9780674995918</identifierValue><source>BNF</source></identifier><identifier><identifierType>ISBN</identifierType><identifierValue>9780674991415</identifierValue><source>BNF</source></identifier><identifier><identifierType>ISBN</identifierType><identifierValue>9780674991385</identifierValue><source>BNF</source></identifier></creativeActivity><personalNameVariant><surname>Quintilian</surname><source>NLN</source></personalNameVariant><personalNameVariant><surname>Quinctilian</surname><source>BAnQ</source></personalNameVariant><personalNameVariant><forename>Marcus Fabius</forename><surname>Quinctilianus</surname><source>BAnQ</source></personalNameVariant><personalNameVariant><surname>Quintilian</surname><source>BAnQ</source></personalNameVariant><personalNameVariant><surname>Quintiliano</surname><source>BAnQ</source></personalNameVariant><personalNameVariant><forename>Marco Fabio</forename><surname>Quintiliano</surname><source>BAnQ</source></personalNameVariant><personalNameVariant><forename>Marcus Fabius</forename><surname>Quintilianus</surname><source>BAnQ</source></personalNameVariant><personalNameVariant><forename>Marco</forename><surname>Fabio Quintiliano</surname><source>VIAF</source><source>BNE</source></personalNameVariant><personalNameVariant><forename>Marcus</forename><surname>Fabius Quintilianus</surname><marcDate>35-100</marcDate><source>VIAF</source><source>DNB</source></personalNameVariant><personalNameVariant><surname>Fabius Quintilianus</surname><marcDate>35-100</marcDate><source>VIAF</source><source>DNB</source></personalNameVariant><personalNameVariant><surname>Fabius</surname><nameTitle>Quintilianus</nameTitle><marcDate>35-100</marcDate><source>VIAF</source><source>DNB</source></personalNameVariant><personalNameVariant><surname>Kintiliano</surname><source>VIAF</source><source>WKP</source></personalNameVariant><personalNameVariant><surname>Kvintilijan</surname><source>VIAF</source><source>PERSEUS</source></personalNameVariant><personalNameVariant><surname>Kvintilijan</surname><source>LCNACO</source></personalNameVariant><personalNameVariant><surname>Kvintilijan</surname><source>VIAF</source><source>WKP</source></personalNameVariant><personalNameVariant><forename>Marko Fabije</forename><surname>Kvintilijan</surname><source>VIAF</source><source>NSK</source></personalNameVariant><personalNameVariant><surname>Kvintiliāns</surname><source>VIAF</source><source>WKP</source></personalNameVariant><personalNameVariant><surname>Kwintylian</surname><source>VIAF</source><source>WKP</source></personalNameVariant><personalNameVariant><forename>M. Fabiusz</forename><surname>Kwintylian</surname><marcDate>ca. 30-ca. 95</marcDate><source>VIAF</source><source>BNC</source></personalNameVariant><personalNameVariant><forename>M. Fabiusz</forename><surname>Kwintylian</surname><source>VIAF</source><source>NLP</source></personalNameVariant><personalNameVariant><forename>M. Fabiusz</forename><surname>Kwintylian</surname><source>VIAF</source><source>NUKAT</source></personalNameVariant><personalNameVariant><surname>Kwintylian</surname><source>VIAF</source><source>NLP</source></personalNameVariant><personalNameVariant><surname>Kwintylian</surname><source>VIAF</source><source>NUKAT</source></personalNameVariant><personalNameVariant><forename>Marek Fabijusz</forename><surname>Kwintylijan</surname><source>VIAF</source><source>NLP</source></personalNameVariant><personalNameVariant><forename>Marek Fabijusz</forename><surname>Kwintylijan</surname><source>VIAF</source><source>NUKAT</source></personalNameVariant><personalNameVariant><forename>Marek Fabjusz</forename><surname>Kwintyljan</surname><source>VIAF</source><source>NLP</source></personalNameVariant><personalNameVariant><forename>Marek Fabjusz</forename><surname>Kwintyljan</surname><source>VIAF</source><source>NUKAT</source></personalNameVariant><personalNameVariant><surname>M. Fabius Quintilianus</surname><source>VIAF</source><source>PERSEUS</source></personalNameVariant><personalNameVariant><surname>M. T. Quintilianus</surname><source>VIAF</source><source>PERSEUS</source></personalNameVariant><personalNameVariant><surname>Marco Fabio Quintiliano</surname><source>VIAF</source><source>WKP</source></personalNameVariant><personalNameVariant><surname>Marcu Fabbiu Quintilianu</surname><source>VIAF</source><source>WKP</source></personalNameVariant><personalNameVariant><surname>Marcus Fabius Quintilian</surname><source>VIAF</source><source>WKP</source></personalNameVariant><personalNameVariant><surname>Marcus Fabius Quintilianus</surname><source>VIAF</source><source>PERSEUS</source></personalNameVariant><personalNameVariant><surname>Marcus Fabius Quintilianus</surname><source>VIAF</source><source>NLP</source></personalNameVariant><personalNameVariant><surname>Marcus Fabius Quintilianus</surname><source>VIAF</source><source>NUKAT</source></personalNameVariant><personalNameVariant><surname>Marko Fabije Kvintilijan</surname><source>VIAF</source><source>WKP</source></personalNameVariant><personalNameVariant><surname>Pseudo-Quintiliano</surname><source>VIAF</source><source>RERO</source></personalNameVariant><personalNameVariant><surname>Pseudo-Quintiliano</surname><marcDate>35-100</marcDate><source>VIAF</source><source>DNB</source></personalNameVariant><personalNameVariant><surname>Pseudo-Quintilianus</surname><source>VIAF</source><source>RERO</source></personalNameVariant><personalNameVariant><forename>Marcus Fabius</forename><surname>Pseudo-Quintilianus</surname><marcDate>35-100</marcDate><source>VIAF</source><source>DNB</source></personalNameVariant><personalNameVariant><surname>Pseudo-Quintilianus</surname><marcDate>35-100</marcDate><source>VIAF</source><source>DNB</source></personalNameVariant><personalNameVariant><surname>QUINT</surname><source>VIAF</source><source>PERSEUS</source></personalNameVariant><personalNameVariant><forename>Marcus F.</forename><surname>Quinctilainus</surname><marcDate>35-100</marcDate><source>VIAF</source><source>DNB</source></personalNameVariant><personalNameVariant><forename>Marcus Fabius</forename><surname>Quinctilainus</surname><marcDate>35-100</marcDate><source>VIAF</source><source>DNB</source></personalNameVariant><personalNameVariant><surname>Quinctilian</surname><source>VIAF</source><source>PERSEUS</source></personalNameVariant><personalNameVariant><surname>Quinctilian</surname><source>VIAF</source><source>B2Q</source></personalNameVariant><personalNameVariant><surname>Quinctilian</surname><source>LCNACO</source></personalNameVariant><personalNameVariant><surname>Quinctilian</surname><marcDate>ca. 30-ca. 95</marcDate><source>VIAF</source><source>BNC</source></personalNameVariant><personalNameVariant><forename>Fabius</forename><surname>Quinctilianus</surname><source>VIAF</source><source>NLI</source></personalNameVariant><personalNameVariant><forename>M. Fabius</forename><surname>Quinctilianus</surname><marcDate>35-100</marcDate><source>VIAF</source><source>DNB</source></personalNameVariant><personalNameVariant><forename>Marcus F.</forename><surname>Quinctilianus</surname><marcDate>35-100</marcDate><source>VIAF</source><source>DNB</source></personalNameVariant><personalNameVariant><forename>Marcus Fabius</forename><surname>Quinctilianus</surname><source>VIAF</source><source>B2Q</source></personalNameVariant><personalNameVariant><forename>Marcus Fabius</forename><surname>Quinctilianus</surname><marcDate>0030?-0100?</marcDate><source>VIAF</source><source>SUDOC</source></personalNameVariant><personalNameVariant><forename>Marcus Fabius</forename><surname>Quinctilianus</surname><marcDate>asi 35-asi 100</marcDate><source>VIAF</source><source>NKC</source></personalNameVariant><personalNameVariant><forename>Marcus Fabius</forename><surname>Quinctilianus</surname><marcDate>ca. 30-ca. 95</marcDate><source>VIAF</source><source>BNC</source></personalNameVariant><personalNameVariant><forename>Marcus Fabius</forename><surname>Quinctilianus</surname><marcDate>35-100</marcDate><source>VIAF</source><source>DNB</source></personalNameVariant><personalNameVariant><surname>Quinctilianus</surname><source>VIAF</source><source>NUKAT</source></personalNameVariant><personalNameVariant><forename>M. Fabiusz</forename><surname>Quinktylian</surname><source>VIAF</source><source>NUKAT</source></personalNameVariant><personalNameVariant><surname>Quint</surname><source>VIAF</source><source>PERSEUS</source></personalNameVariant><personalNameVariant><forename>Marcus Fabius</forename><surname>Quintilen</surname><marcDate>35-100</marcDate><source>VIAF</source><source>DNB</source></personalNameVariant><personalNameVariant><surname>Quintilian</surname><source>VIAF</source><source>B2Q</source></personalNameVariant><personalNameVariant><surname>Quintilian</surname><source>VIAF</source><source>NSK</source></personalNameVariant><personalNameVariant><surname>Quintilian</surname><source>VIAF</source><source>RERO</source></personalNameVariant><personalNameVariant><surname>Quintilian</surname><source>VIAF</source><source>BNE</source></personalNameVariant><personalNameVariant><forename>M. Fabi</forename><surname>Quintilian</surname><source>VIAF</source><source>NSK</source></personalNameVariant><personalNameVariant><forename>Marcus Fabius</forename><surname>Quintilian</surname><marcDate>35-100</marcDate><source>VIAF</source><source>DNB</source></personalNameVariant><personalNameVariant><forename>Marcus</forename><surname>Quintilian</surname><marcDate>35-100</marcDate><source>VIAF</source><source>DNB</source></personalNameVariant><personalNameVariant><surname>Quintilian</surname><marcDate>0030?-0100?</marcDate><source>VIAF</source><source>SUDOC</source></personalNameVariant><personalNameVariant><surname>Quintilian</surname><marcDate>ca 35-ca 100</marcDate><source>NLS</source></personalNameVariant><personalNameVariant><surname>Quintilian</surname><marcDate>ca. 30-ca. 95</marcDate><source>VIAF</source><source>BNC</source></personalNameVariant><personalNameVariant><surname>Quintilian</surname><source>VIAF</source><source>NUKAT</source></personalNameVariant><personalNameVariant><surname>Quintiliano</surname><source>VIAF</source><source>PERSEUS</source></personalNameVariant><personalNameVariant><surname>Quintiliano</surname><source>VIAF</source><source>ICCU</source></personalNameVariant><personalNameVariant><surname>Quintiliano</surname><source>VIAF</source><source>B2Q</source></personalNameVariant><personalNameVariant><surname>Quintiliano</surname><source>LCNACO</source></personalNameVariant><personalNameVariant><surname>Quintiliano</surname><source>VIAF</source><source>WKP</source></personalNameVariant><personalNameVariant><surname>Quintiliano</surname><source>VIAF</source><source>BNE</source></personalNameVariant><personalNameVariant><forename>M. F.</forename><surname>Quintiliano</surname><source>VIAF</source><source>BNE</source></personalNameVariant><personalNameVariant><forename>M. Fabio</forename><surname>Quintiliano</surname><source>VIAF</source><source>BNE</source></personalNameVariant><personalNameVariant><forename>M. Fabio</forename><surname>Quintiliano</surname><marcDate>ca 35-ca 100</marcDate><source>NLS</source></personalNameVariant><personalNameVariant><forename>Marco Fabio</forename><surname>Quintiliano</surname><source>VIAF</source><source>PERSEUS</source></personalNameVariant><personalNameVariant><forename>Marco Fabio</forename><surname>Quintiliano</surname><source>VIAF</source><source>B2Q</source></personalNameVariant><personalNameVariant><forename>Marco Fabio</forename><surname>Quintiliano</surname><source>LCNACO</source></personalNameVariant><personalNameVariant><forename>Marco Fabio</forename><surname>Quintiliano</surname><source>VIAF</source><source>RERO</source></personalNameVariant><personalNameVariant><forename>Marco Fabio</forename><surname>Quintiliano</surname><marcDate>asi 35-asi 100</marcDate><source>VIAF</source><source>NKC</source></personalNameVariant><personalNameVariant><forename>Marco Fabio</forename><surname>Quintiliano</surname><marcDate>c. 35-c. 96</marcDate><source>VIAF</source><source>BAV</source></personalNameVariant><personalNameVariant><forename>Marco Fabio</forename><surname>Quintiliano</surname><marcDate>ca 35-ca 100</marcDate><source>NLS</source></personalNameVariant><personalNameVariant><forename>Marco Fabio</forename><surname>Quintiliano</surname><marcDate>ca. 30-ca. 95</marcDate><source>VIAF</source><source>BNC</source></personalNameVariant><personalNameVariant><forename>Marco Fabio</forename><surname>Quintiliano</surname><marcDate>35-100</marcDate><source>VIAF</source><source>DNB</source></personalNameVariant><personalNameVariant><surname>Quintiliano</surname><marcDate>0030?-0100?</marcDate><source>VIAF</source><source>SUDOC</source></personalNameVariant><personalNameVariant><surname>Quintiliano</surname><nameTitle>Marco Fábio</nameTitle><source>VIAF</source><source>PTBNP</source></personalNameVariant><personalNameVariant><surname>Quintiliano</surname><marcDate>asi 35-asi 100</marcDate><source>VIAF</source><source>NKC</source></personalNameVariant><personalNameVariant><surname>Quintiliano</surname><marcDate>ca 35-ca 100</marcDate><source>NLS</source></personalNameVariant><personalNameVariant><surname>Quintiliano</surname><marcDate>ca. 30-ca. 95</marcDate><source>VIAF</source><source>BNC</source></personalNameVariant><personalNameVariant><surname>Quintiliano</surname><nameTitle>, Marco Fabio</nameTitle><source>VIAF</source><source>ICCU</source></personalNameVariant><personalNameVariant><surname>Quintiliano</surname><marcDate>35-100</marcDate><source>VIAF</source><source>DNB</source></personalNameVariant><personalNameVariant><surname>Quintiliano</surname><nameTitle>de Calahorra</nameTitle><marcDate>35-100</marcDate><source>VIAF</source><source>DNB</source></personalNameVariant><personalNameVariant><surname>Quintilianu</surname><source>VIAF</source><source>WKP</source></personalNameVariant><personalNameVariant><surname>Quintilianus</surname><source>VIAF</source><source>SUDOC</source></personalNameVariant><personalNameVariant><surname>Quintilianus</surname><source>VIAF</source><source>WKP</source></personalNameVariant><personalNameVariant><forename>Fabius</forename><surname>Quintilianus</surname><marcDate>35-100</marcDate><source>VIAF</source><source>DNB</source></personalNameVariant><personalNameVariant><forename>M. Fabius</forename><surname>Quintilianus</surname><source>VIAF</source><source>NLP</source></personalNameVariant><personalNameVariant><forename>M. Fabius</forename><surname>Quintilianus</surname><source>VIAF</source><source>NUKAT</source></personalNameVariant><personalNameVariant><forename>M. Fabius</forename><surname>Quintilianus</surname><marcDate>35-100</marcDate><source>VIAF</source><source>DNB</source></personalNameVariant><personalNameVariant><forename>M. Fabi</forename><surname>Quintilianus</surname><marcDate>35-100</marcDate><source>VIAF</source><source>DNB</source></personalNameVariant><personalNameVariant><forename>Marcus F.</forename><surname>Quintilianus</surname><marcDate>35-100</marcDate><source>VIAF</source><source>DNB</source></personalNameVariant><personalNameVariant><forename>Marcus Fabius</forename><surname>Quintilianus</surname><source>VIAF</source><source>PERSEUS</source></personalNameVariant><personalNameVariant><forename>Marcus Fabius</forename><surname>Quintilianus</surname><source>VIAF</source><source>B2Q</source></personalNameVariant><personalNameVariant><forename>Marcus Fabius</forename><surname>Quintilianus</surname><source>VIAF</source><source>NLI</source></personalNameVariant><personalNameVariant><forename>Marcus Fabius</forename><surname>Quintilianus</surname><source>VIAF</source><source>BNE</source></personalNameVariant><personalNameVariant><forename>Marcus Fabius</forename><surname>Quintilianus</surname><marcDate>ca 35-ca 100</marcDate><source>NLS</source></personalNameVariant><personalNameVariant><forename>Marcus Fabius</forename><surname>Quintilianus</surname><marcDate>ca. 30-ca. 95</marcDate><source>VIAF</source><source>BNC</source></personalNameVariant><personalNameVariant><forename>Marcus Fabius</forename><surname>Quintilianus</surname><source>LCNACO</source></personalNameVariant><personalNameVariant><forename>Marcus Fabius</forename><surname>Quintilianus</surname><marcDate>35-100</marcDate><source>VIAF</source><source>DNB</source></personalNameVariant><personalNameVariant><forename>Marcus T.</forename><surname>Quintilianus</surname><marcDate>35-100</marcDate><source>VIAF</source><source>DNB</source></personalNameVariant><personalNameVariant><surname>Quintilianus</surname><nameTitle>Marcus Fabius</nameTitle><source>VIAF</source><source>PTBNP</source></personalNameVariant><personalNameVariant><surname>Quintilianus</surname><marcDate>35-100</marcDate><source>VIAF</source><source>DNB</source></personalNameVariant><personalNameVariant><surname>Quintilianus</surname><nameTitle>Calagurritanus</nameTitle><marcDate>35-100</marcDate><source>VIAF</source><source>DNB</source></personalNameVariant><personalNameVariant><surname>Quintilianus</surname><nameTitle>Pseudo-</nameTitle><marcDate>35-100</marcDate><source>VIAF</source><source>DNB</source></personalNameVariant><personalNameVariant><surname>Quintilianus</surname><nameTitle>Rhetorician</nameTitle><marcDate>35-100</marcDate><source>VIAF</source><source>DNB</source></personalNameVariant><personalNameVariant><surname>Quintilianus</surname><nameTitle>Rhetor</nameTitle><marcDate>35-100</marcDate><source>VIAF</source><source>DNB</source></personalNameVariant><personalNameVariant><surname>Quintilianus</surname><nameTitle>Tarraconensis</nameTitle><marcDate>35-100</marcDate><source>VIAF</source><source>DNB</source></personalNameVariant><personalNameVariant><surname>Quintilianus</surname><nameTitle>ex Hispania Tarraconensi</nameTitle><marcDate>35-100</marcDate><source>VIAF</source><source>DNB</source></personalNameVariant><personalNameVariant><surname>Quintilianus</surname><nameTitle>ex Hispania</nameTitle><marcDate>35-100</marcDate><source>VIAF</source><source>DNB</source></personalNameVariant><personalNameVariant><surname>Quintilianus</surname><nameTitle>von Calagurris</nameTitle><marcDate>35-100</marcDate><source>VIAF</source><source>DNB</source></personalNameVariant><personalNameVariant><surname>Quintilianus</surname><nameTitle>von Spanien</nameTitle><marcDate>35-100</marcDate><source>VIAF</source><source>DNB</source></personalNameVariant><personalNameVariant><surname>Quintilian</surname><marcDate>35-100</marcDate><source>VIAF</source><source>DNB</source></personalNameVariant><personalNameVariant><surname>Quintilian</surname><nameTitle>ancient roman rhetor</nameTitle><source>VIAF</source><source>WKP</source></personalNameVariant><personalNameVariant><surname>Quintilian</surname><nameTitle>römischer Redelehrer und Prinzenerzieher am Kaiserhof Domitians</nameTitle><source>VIAF</source><source>WKP</source></personalNameVariant><personalNameVariant><surname>Quintilien</surname><source>VIAF</source><source>PERSEUS</source></personalNameVariant><personalNameVariant><surname>Quintilien</surname><source>VIAF</source><source>ICCU</source></personalNameVariant><personalNameVariant><surname>Quintilien</surname><source>VIAF</source><source>NLI</source></personalNameVariant><personalNameVariant><surname>Quintilien</surname><source>VIAF</source><source>RERO</source></personalNameVariant><personalNameVariant><surname>Quintilien</surname><source>LCNACO</source></personalNameVariant><personalNameVariant><surname>Quintilien</surname><source>VIAF</source><source>WKP</source></personalNameVariant><personalNameVariant><surname>Quintilien</surname><source>VIAF</source><source>BNE</source></personalNameVariant><personalNameVariant><surname>Quintilien</surname><marcDate>ca 30-ca 100)</marcDate><source>VIAF</source><source>NLP</source></personalNameVariant><personalNameVariant><surname>Quintilien</surname><marcDate>ca 30-ca 100)</marcDate><source>VIAF</source><source>NUKAT</source></personalNameVariant><personalNameVariant><surname>Quintilien</surname><marcDate>asi 35-asi 100</marcDate><source>VIAF</source><source>NKC</source></personalNameVariant><personalNameVariant><surname>Quintilien</surname><marcDate>ca 35-ca 100</marcDate><source>NLS</source></personalNameVariant><personalNameVariant><surname>Quintilien</surname><marcDate>ca. 30-ca. 95</marcDate><source>VIAF</source><source>BNC</source></personalNameVariant><personalNameVariant><surname>Quintilien</surname><marcDate>35-100</marcDate><source>VIAF</source><source>DNB</source></personalNameVariant><personalNameVariant><surname>Quintilien</surname><nameTitle>de Calagurris</nameTitle><marcDate>35-100</marcDate><source>VIAF</source><source>DNB</source></personalNameVariant><personalNameVariant><surname>Quintilià</surname><source>VIAF</source><source>PERSEUS</source></personalNameVariant><personalNameVariant><surname>Quintilià</surname><source>VIAF</source><source>WKP</source></personalNameVariant><personalNameVariant><forename>M. F.</forename><surname>Quintilià</surname><marcDate>ca. 30-ca. 95</marcDate><source>VIAF</source><source>BNC</source></personalNameVariant><personalNameVariant><forename>M. F.</forename><surname>Quintilià</surname><marcDate>ca. 30-ca. 95</marcDate><source>VIAF</source><source>BNC</source></personalNameVariant><personalNameVariant><forename>M. Fabio</forename><surname>Quintilià</surname><marcDate>ca. 30-ca. 95</marcDate><source>VIAF</source><source>BNC</source></personalNameVariant><personalNameVariant><forename>Marc Fabi</forename><surname>Quintilià</surname><source>VIAF</source><source>BNE</source></personalNameVariant><personalNameVariant><forename>Marc Fabi</forename><surname>Quintilià</surname><source>VIAF</source><source>BNC</source></personalNameVariant><personalNameVariant><forename>Marc Fabi</forename><surname>Quintilià</surname><marcDate>30?-95?</marcDate><source>VIAF</source><source>BNC</source></personalNameVariant><personalNameVariant><surname>Quintilià</surname><marcDate>ca. 30-ca. 95</marcDate><source>VIAF</source><source>BNC</source></personalNameVariant><personalNameVariant><surname>Quintillian</surname><source>LCNACO</source></personalNameVariant><personalNameVariant><surname>Quintilliano</surname><nameTitle>, M. Fabio</nameTitle><source>VIAF</source><source>ICCU</source></personalNameVariant><personalNameVariant><surname>[QUINT.]</surname><source>VIAF</source><source>PERSEUS</source></personalNameVariant><personalNameVariant><surname>Квинтилиан</surname><nameTitle>древнеримский оратор, руководитель первой государственной школы риторики, реформатор литературного стиля</nameTitle><source>VIAF</source><source>WKP</source></personalNameVariant><personalNameVariant><surname>Квінтиліан</surname><source>VIAF</source><source>WKP</source></personalNameVariant><personalNameVariant><surname>Марко Фабиј Квинтилијан</surname><source>VIAF</source><source>WKP</source></personalNameVariant><personalNameVariant><surname>Марко Фабије Квинтилијан</surname><source>VIAF</source><source>WKP</source></personalNameVariant><personalNameVariant><surname>Քվինթիլիանուս</surname><source>VIAF</source><source>WKP</source></personalNameVariant><personalNameVariant><surname>קוינטיליאנוס</surname><source>VIAF</source><source>WKP</source></personalNameVariant><personalNameVariant><surname>کوئنتیلی</surname><source>VIAF</source><source>WKP</source></personalNameVariant><personalNameVariant><surname>クインティリアヌス</surname><source>VIAF</source><source>PERSEUS</source></personalNameVariant><personalNameVariant><surname>クインティリアヌス</surname><source>VIAF</source><source>WKP</source></personalNameVariant><personalNameVariant><surname>クインティリアーヌス</surname><source>VIAF</source><source>NDL</source></personalNameVariant><personalNameVariant><surname>昆体良</surname><source>LCNACO</source></personalNameVariant><personalNameVariant><surname>昆提利安</surname><source>VIAF</source><source>WKP</source></personalNameVariant><personalNameVariant><surname>마르쿠스 파비우스 퀸틸리아누스</surname><source>VIAF</source><source>WKP</source></personalNameVariant><personalNameVariant><forename>M. Fabius</forename><surname>Quinctilianus</surname><marcDate>ca35-96</marcDate><source>NTA</source></personalNameVariant><personalNameVariant><surname>Quintilian</surname><marcDate>ca35-96</marcDate><source>NTA</source></personalNameVariant><personalNameVariant><surname>Quintiliano</surname><marcDate>ca35-96</marcDate><source>NTA</source></personalNameVariant><personalNameVariant><forename>Fabius</forename><surname>Quintilianus</surname><marcDate>ca35-96</marcDate><source>NTA</source></personalNameVariant><personalNameVariant><surname>Quintilianus</surname><marcDate>ca35-96</marcDate><source>NTA</source></personalNameVariant><personalNameVariant><surname>Quintilien</surname><marcDate>ca35-96</marcDate><source>NTA</source></personalNameVariant><personalNameVariant><forename>Marcus Fabius</forename><surname>Quinctilianus</surname><marcDate>0030?-0100?</marcDate><source>BNF</source></personalNameVariant><personalNameVariant><forename>Marco Fabio</forename><surname>Quintiliano</surname><marcDate>0030?-0100?</marcDate><source>BNF</source></personalNameVariant><personalNameVariant><surname>Quintilianus Rhetor</surname><marcDate>0030?-0100?</marcDate><source>BNF</source></personalNameVariant><personalNameVariant><forename>Marcus Fabius</forename><surname>Quintilianus</surname><marcDate>0030?-0100?</marcDate><source>BNF</source></personalNameVariant><personalNameVariant><surname>Quintilian</surname><marcDate>0030?-0100?</marcDate><source>BNF</source></personalNameVariant><personalNameVariant><forename>Marc Fabi</forename><surname>Quintilià</surname><marcDate>0030?-0100?</marcDate><source>BNF</source></personalNameVariant><otherIdentifierOfIdentity><type>VIAF</type><identifier>34451872</identifier><source>OCLCT</source></otherIdentifierOfIdentity><sources><codeOfSource>OCLCT</codeOfSource><sourceIdentifier>250876124</sourceIdentifier></sources><sources><codeOfSource>VIAF</codeOfSource><sourceIdentifier>34451872</sourceIdentifier><reference><class>ALL</class><role>CRE</role><URI>http://viaf.org/viaf/34451872</URI></reference></sources><sources><codeOfSource>BNF</codeOfSource><sourceIdentifier>11887333</sourceIdentifier></sources><sources><codeOfSource>NTA</codeOfSource><sourceIdentifier>069261555</sourceIdentifier></sources><sources><codeOfSource>BAnQ</codeOfSource><sourceIdentifier>0000948706</sourceIdentifier></sources><sources><codeOfSource>NLFIN</codeOfSource><sourceIdentifier>(FI-ASTERI-N)000113915</sourceIdentifier></sources><sources><codeOfSource>NLN</codeOfSource><sourceIdentifier>90142868</sourceIdentifier></sources><sources><codeOfSource>NLS</codeOfSource><sourceIdentifier>197294</sourceIdentifier></sources><sources><codeOfSource>LCNACO</codeOfSource><sourceIdentifier>n  80046563</sourceIdentifier></sources><externalInformation><information>Wikipedia</information><URI>https://ast.wikipedia.org/wiki/Quintiliano</URI></externalInformation><externalInformation><information>Wikipedia</information><URI>https://bg.wikipedia.org/wiki/Квинтилиан</URI></externalInformation><externalInformation><information>Wikipedia</information><URI>https://ca.wikipedia.org/wiki/Quintilià</URI></externalInformation><externalInformation><information>Wikipedia</information><URI>https://cs.wikipedia.org/wiki/Marcus_Fabius_Quintilianus</URI></externalInformation><externalInformation><information>Wikipedia</information><URI>https://da.wikipedia.org/wiki/Marcus_Fabius_Quintilian</URI></externalInformation><externalInformation><information>Wikipedia</information><URI>https://de.wikipedia.org/wiki/Quintilian</URI></externalInformation><externalInformation><information>Wikipedia</information><URI>https://en.wikipedia.org/wiki/Quintilian</URI></externalInformation><externalInformation><information>Wikipedia</information><URI>https://eo.wikipedia.org/wiki/Kvintiliano</URI></externalInformation><externalInformation><information>Wikipedia</information><URI>https://es.wikipedia.org/wiki/Quintiliano</URI></externalInformation><externalInformation><information>Wikipedia</information><URI>https://eu.wikipedia.org/wiki/Kintiliano</URI></externalInformation><externalInformation><information>Wikipedia</information><URI>https://ext.wikipedia.org/wiki/Quintilianu</URI></externalInformation><externalInformation><information>Wikipedia</information><URI>https://fa.wikipedia.org/wiki/کوئنتیلی</URI></externalInformation><externalInformation><information>Wikipedia</information><URI>https://fi.wikipedia.org/wiki/Quintilianus</URI></externalInformation><externalInformation><information>Wikipedia</information><URI>https://fr.wikipedia.org/wiki/Quintilien</URI></externalInformation><externalInformation><information>Wikipedia</information><URI>https://gl.wikipedia.org/wiki/Quintiliano</URI></externalInformation><externalInformation><information>Wikipedia</information><URI>https://he.wikipedia.org/wiki/קווינטיליאנוס</URI></externalInformation><externalInformation><information>Wikipedia</information><URI>https://hu.wikipedia.org/wiki/Marcus_Fabius_Quintilianus</URI></externalInformation><externalInformation><information>Wikipedia</information><URI>https://hy.wikipedia.org/wiki/Քվինթիլիանուս</URI></externalInformation><externalInformation><information>Wikipedia</information><URI>https://is.wikipedia.org/wiki/Quintilianus</URI></externalInformation><externalInformation><information>Wikipedia</information><URI>https://it.wikipedia.org/wiki/Marco_Fabio_Quintiliano</URI></externalInformation><externalInformation><information>Wikipedia</information><URI>https://ja.wikipedia.org/wiki/クインティリアヌス</URI></externalInformation><externalInformation><information>Wikipedia</information><URI>https://ko.wikipedia.org/wiki/마르쿠스_파비우스_퀸틸리아누스</URI></externalInformation><externalInformation><information>Wikipedia</information><URI>https://la.wikipedia.org/wiki/Marcus_Fabius_Quintilianus</URI></externalInformation><externalInformation><information>Wikipedia</information><URI>https://lv.wikipedia.org/wiki/Kvintiliāns</URI></externalInformation><externalInformation><information>Wikipedia</information><URI>https://mk.wikipedia.org/wiki/Марко_Фабиј_Квинтилијан</URI></externalInformation><externalInformation><information>Wikipedia</information><URI>https://nl.wikipedia.org/wiki/Marcus_Fabius_Quintilianus</URI></externalInformation><externalInformation><information>Wikipedia</information><URI>https://nn.wikipedia.org/wiki/Marcus_Fabius_Quintilianus</URI></externalInformation><externalInformation><information>Wikipedia</information><URI>https://no.wikipedia.org/wiki/Marcus_Fabius_Quintilianus</URI></externalInformation><externalInformation><information>Wikipedia</information><URI>https://pl.wikipedia.org/wiki/Kwintylian</URI></externalInformation><externalInformation><information>Wikipedia</information><URI>https://pt.wikipedia.org/wiki/Quintiliano</URI></externalInformation><externalInformation><information>Wikipedia</information><URI>https://ro.wikipedia.org/wiki/Quintilian</URI></externalInformation><externalInformation><information>Wikipedia</information><URI>https://ru.wikipedia.org/wiki/Квинтилиан</URI></externalInformation><externalInformation><information>Wikipedia</information><URI>https://scn.wikipedia.org/wiki/Marcu_Fabbiu_Quintilianu</URI></externalInformation><externalInformation><information>Wikipedia</information><URI>https://sco.wikipedia.org/wiki/Quintilian</URI></externalInformation><externalInformation><information>Wikipedia</information><URI>https://sh.wikipedia.org/wiki/Kvintilijan</URI></externalInformation><externalInformation><information>Wikipedia</information><URI>https://sk.wikipedia.org/wiki/Marcus_Fabius_Quintilianus</URI></externalInformation><externalInformation><information>Wikipedia</information><URI>https://sr.wikipedia.org/wiki/Marko_Fabije_Kvintilijan</URI></externalInformation><externalInformation><information>Wikipedia</information><URI>https://sv.wikipedia.org/wiki/Marcus_Fabius_Quintilianus</URI></externalInformation><externalInformation><information>Wikipedia</information><URI>https://tr.wikipedia.org/wiki/Marcus_Fabius_Quintilianus</URI></externalInformation><externalInformation><information>Wikipedia</information><URI>https://uk.wikipedia.org/wiki/Квінтиліан</URI></externalInformation><externalInformation><information>Wikipedia</information><URI>https://zh.wikipedia.org/wiki/昆提利安</URI></externalInformation></ISNIAssigned>