<ISNIAssigned><isniUnformatted>0000000081273289</isniUnformatted><isniURI>https://isni.org/isni/0000000081273289</isniURI><dataConfidence>60</dataConfidence><personalName><forename>William</forename><surname>Fleetwood</surname><marcDate>1656-1723</marcDate><nameUse>public</nameUse><source>LCNACO</source></personalName><personalName><forename>William</forename><surname>Fleetwood</surname><marcDate>1656-1723</marcDate><nameUse>public</nameUse><source>VIAF</source><source>DNB</source><subsourceIdentifier>13031661X</subsourceIdentifier></personalName><personalName><forename>William</forename><surname>Fleetwood</surname><nameTitle>bp. of Ely</nameTitle><marcDate>1656-1723</marcDate><nameUse>public</nameUse><source>VIAF</source><source>BAV</source><subsourceIdentifier>ADV10216568</subsourceIdentifier></personalName><personalName><forename>William,</forename><surname>Fleetwood</surname><marcDate>1656-1723</marcDate><nameUse>public</nameUse><source>VIAF</source><source>N6I</source><subsourceIdentifier>vtls000029422</subsourceIdentifier></personalName><personalName><forename>William,</forename><surname>Fleetwood</surname><marcDate>1656-1723</marcDate><nameUse>public</nameUse><source>VIAF</source><source>SUDOC</source><subsourceIdentifier>028972422</subsourceIdentifier></personalName><personalName><forename>William,</forename><surname>Fleetwood</surname><marcDate>1656-1723</marcDate><nameUse>public</nameUse><source>VIAF</source><source>NLI</source><subsourceIdentifier>000449971</subsourceIdentifier></personalName><personalName><forename>Guillaume d'</forename><surname>Occam</surname><nameUse>public</nameUse><source>VIAF</source><source>PTBNP</source><subsourceIdentifier>1215484</subsourceIdentifier></personalName><personalName><surname>William Fleetwood</surname><nameUse>public</nameUse><source>VIAF</source><source>WKP</source><subsourceIdentifier>Q8009143</subsourceIdentifier></personalName><personalName><surname>William of Ockham</surname><nameUse>public</nameUse><source>VIAF</source><source>NSK</source><subsourceIdentifier>000258608</subsourceIdentifier></personalName><personalName><forename>William,</forename><surname>Fleetwood</surname><marcDate>1656-1723</marcDate><nameUse>public</nameUse><source>NTA</source></personalName><personalName><forename>William</forename><surname>Fleetwood</surname><marcDate>1656-1723</marcDate><nameUse>public</nameUse><source>BNF</source><subsourceIdentifier>12069721</subsourceIdentifier></personalName><creativeActivity><creationRole source="LCNACO">aut</creationRole><creationClass source="LCNACO">am</creationClass><creationClass source="VIAF" subsource="N6I">am</creationClass><creationClass source="VIAF" subsource="SUDOC">am</creationClass><creationClass source="VIAF" subsource="PTBNP">am</creationClass><creationClass source="VIAF" subsource="NSK">am</creationClass><creationClass source="VIAF" subsource="BAV">am</creationClass><creationClass source="VIAF" subsource="SUDOC">mm</creationClass><creationClass source="NTA">am</creationClass><creationClass source="BNF">am</creationClass><titleOfWork source="LCNACO"><title>A @sermon preached before the Society for the Propagation of the Gospel in Foreign Parts</title></titleOfWork><titleOfWork source="VIAF" subsource="SUDOC"><title>The @account of the true market-price of wheat, and malt, at Windsor, for 100 years - Began &#38; publish'd by Wm. Fleetwood Bp. of Ely from 1646. to 1706. And since continued in the same manner.</title></titleOfWork><titleOfWork source="VIAF" subsource="SUDOC"><title>The @Bishop of Ely's thanksgiving-sermon, preach'd on the seventh of June, 1716. Done into verse</title></titleOfWork><titleOfWork source="VIAF" subsource="PTBNP"><title>@Breviloquium de Potestate Papae</title></titleOfWork><titleOfWork source="VIAF" subsource="SUDOC"><title>A @charge, delivered to the clergy of the diocese of Ely In August, 1722. By William late Lord Bishop of Ely.</title></titleOfWork><titleOfWork source="VIAF" subsource="N6I"><title>@Chronicon preciosum or, an account of English money, the price of corn, and other commodities, for the last 600 years. In a letter to a student in the University of Oxford.</title></titleOfWork><titleOfWork source="VIAF" subsource="SUDOC"><title>@Chronicon preciosum or, an account of English money, the price of corn, and other commodities, for the last 600 years. In a letter to a student in the University of Oxford.</title></titleOfWork><titleOfWork source="VIAF" subsource="DNB"><title>@Chronicon preciosum or, an account of English money, the price of corn, and other commodities, for the last 600 years. In a letter to a student in the University of Oxford.</title></titleOfWork><titleOfWork source="VIAF" subsource="SUDOC"><title>A @collection of papers</title></titleOfWork><titleOfWork source="VIAF" subsource="SUDOC"><title>The @curate of Wilts his second letter to the Reverend Dr. Snape or, reasons against the bill now depending in the House of Commons.</title></titleOfWork><titleOfWork source="VIAF" subsource="SUDOC"><title>A @defence of praying before sermon, as directed by the LVth canon</title></titleOfWork><titleOfWork source="VIAF" subsource="N6I"><title>The @family New Year's gift: or, A present for a son or a daughter, 1745:</title></titleOfWork><titleOfWork source="VIAF" subsource="SUDOC"><title>@Four sermons I. On the death of Queen Mary, 1694. II. On the death of the Duke of Gloucester, 1700. III. On the death of King William, 1701. IV. On the Queen's accession to the throne, in 1703. By William Lord Bishop of St. Asaph.</title></titleOfWork><titleOfWork source="VIAF" subsource="SUDOC"><title>@Funeral sermon upon Mr. Noble By a neighbouring minister.</title></titleOfWork><titleOfWork source="VIAF" subsource="SUDOC"><title>@Inscriptionum antiquarum sylloge...</title><subtitle>a Guil. Fleetwood,....</subtitle></titleOfWork><titleOfWork source="VIAF" subsource="DNB"><title>@Inscriptionum antiquarum sylloge...</title><subtitle>a Guil. Fleetwood,....</subtitle></titleOfWork><titleOfWork source="VIAF" subsource="BAV"><title>@Inscriptionum antiquarum sylloge in duas partes distributa. Quarum prior inscriptiones ethnieas singulares &#38; rariores penè omnes continet, quae vel Gruteri Corpore, Reynesii Syntagmate, Sponii Miscellaneis, aliisque ejusdem argumenti libris reperiuntur. Altera chistiana monumenta antiqua quae hactenus innotuerunt omnia complectitur. In usum juventutis rerun antiquarum studiosae edita, &#38; notis quibusdam illustrata:</title></titleOfWork><titleOfWork source="VIAF" subsource="SUDOC"><title>The @justice of paying debts a sermon preach'd in the city</title></titleOfWork><titleOfWork source="VIAF" subsource="SUDOC"><title>A @letter to an inhabitant of the parish of St. Andrew's Holbourn about new ceremonies in the church.</title></titleOfWork><titleOfWork source="VIAF" subsource="SUDOC"><title>A @letter to the Reverend Dr. Snape wherein the authority of the Christian priesthood is maintain'd; the uninterrupted succession of bishops from the Apostles days is lineally deduced; ... By a curate of Wilts.</title></titleOfWork><titleOfWork source="VIAF" subsource="DNB"><title>@Life and death of the Virgin Mary</title></titleOfWork><titleOfWork source="VIAF" subsource="NLI"><title>@Life and death of the Virgin Mary</title></titleOfWork><titleOfWork source="VIAF" subsource="N6I"><title>@Life and death of the Virgin Mary</title></titleOfWork><titleOfWork source="VIAF" subsource="SUDOC"><title>The @life and miracles of St. Wenefrede together with her Litanies; with some historical observations made thereon.</title></titleOfWork><titleOfWork source="VIAF" subsource="N6I"><title>The @life and miracles of St. Wenefrede together with her Litanies; with some historical observations made thereon.</title></titleOfWork><titleOfWork source="VIAF" subsource="NSK"><title>@Opera politica</title></titleOfWork><titleOfWork source="VIAF" subsource="SUDOC"><title>@Papists not excluded from the throne upon the account of religion. Being a vindication of the ... Bishop of Bangor's Preservative, &#38;c. in that particular. In a short dialogue.</title></titleOfWork><titleOfWork source="VIAF" subsource="NLI"><title>A @plain method of Christian devotion, 1692:</title></titleOfWork><titleOfWork source="VIAF" subsource="N6I"><title>A @plain method of Christian devotion, 1692:</title></titleOfWork><titleOfWork source="VIAF" subsource="NSK"><title>@Quodlibeta septem</title></titleOfWork><titleOfWork source="VIAF" subsource="NSK"><title>@Quodlibetal questions</title><subtitle>Quodlibets 1-7</subtitle><statementOfResponsibility>William of Ockham. New Haven, 1991.</statementOfResponsibility></titleOfWork><titleOfWork source="VIAF" subsource="SUDOC"><title>The @reasonable communicant or, an explanation of the doctrine of the sacrament of the Lord's Supper, in all its parts, from the communion service. In a discourse between a minister and one of his parishioners. By W. Fleetwood.</title></titleOfWork><titleOfWork source="VIAF" subsource="SUDOC"><title>The @relative duties of parents and children husbands and wives, masters and servants; consider'd in sixteen practical discourses: with three sermons upon the case of self-murther. By William Fleetwood.</title></titleOfWork><titleOfWork source="VIAF" subsource="N6I"><title>The @relative duties of parents and children husbands and wives, masters and servants; consider'd in sixteen practical discourses: with three sermons upon the case of self-murther. By William Fleetwood.</title></titleOfWork><titleOfWork source="VIAF" subsource="SUDOC"><title>The @second part of The judgment of the Church of England, in the case of lay-baptism, and dissenters baptism</title></titleOfWork><titleOfWork source="VIAF" subsource="SUDOC"><title>A @sermon against clipping preach'd before the Right Honourable the Lord Mayor and Court of Aldermen</title></titleOfWork><titleOfWork source="VIAF" subsource="DNB"><title>A @sermon against clipping preach'd before the Right Honourable the Lord Mayor and Court of Aldermen</title></titleOfWork><titleOfWork source="VIAF" subsource="SUDOC"><title>A @sermon on the fast-day, January the sixteenth, 1711/12 against such as delight in war. By a divine of the Church of England.</title></titleOfWork><titleOfWork source="VIAF" subsource="SUDOC"><title>@Sermon preach'd at Ely-House chapel, in Holbourn, on Thursday June the 7th, 1716</title></titleOfWork><titleOfWork source="VIAF" subsource="SUDOC"><title>@Sermon preach'd August the 4th 1700</title></titleOfWork><titleOfWork source="VIAF" subsource="DNB"><title>@Sermon preach'd August the 4th 1700</title></titleOfWork><titleOfWork source="VIAF" subsource="DNB"><title>A @sermon preach'd before the Queen at White-Hall February the 12th *. -</title></titleOfWork><titleOfWork source="VIAF" subsource="DNB"><title>A @sermon preached ... at Christ-Church ... St. Stephen's day. -</title></titleOfWork><titleOfWork source="VIAF" subsource="DNB"><title>A @sermon preached ... at Guild-Hall chapel, Dec. the XI. 1692, befo*. -</title></titleOfWork><titleOfWork source="VIAF" subsource="N6I"><title>A @sermon preached before the Society for the Propagation of the Gospel in Foreign Parts, 1711:</title></titleOfWork><titleOfWork source="VIAF" subsource="SUDOC"><title>A @sermon preached on September the 7th. Being the day appointed for the thanksgiving. By W. Fleetwood</title></titleOfWork><titleOfWork source="VIAF" subsource="SUDOC"><title>A @sermon upon swearing Preached at his parish. By William, late Lord Bishop of S. Asaph.</title></titleOfWork><titleOfWork source="VIAF" subsource="SUDOC"><title>@Seventeen sermons preach'd upon several occasions. By W. Fleetwood, ... First collected together.</title></titleOfWork><titleOfWork source="VIAF" subsource="SUDOC"><title>The @thirteenth chapter to the Romans vindicated from the abusive senses put upon it. Written by a curate of Salop; and directed to the clergy of that county, and the neighbouring ones of North-Wales.</title></titleOfWork><titleOfWork source="VIAF" subsource="PTBNP"><title>Le @tractatus de Principiis Theologiae attribué à G. d'Occam</title></titleOfWork><titleOfWork source="VIAF" subsource="SUDOC"><title>@William Fleetwood's ... Gründliche Untersuchung Der Wunder-Wercke, Worinnen nicht alleine die Beschaffenheit der wahren Wunder beschrieben ... sondern ... erwiesen wird, wie der Teuffel keine Wunder thun könne, und also die Wunder der Aegyptischen Zauberer ... durch Gottes Macht geschehen. Am Ende sind beygefüget M. Pascals Sonderbahre Gedancken von Wundern</title></titleOfWork><titleOfWork source="VIAF" subsource="DNB"><title>@William Fleetwood's ... Gründliche Untersuchung Der Wunder-Wercke, Worinnen nicht alleine die Beschaffenheit der wahren Wunder beschrieben ... sondern ... erwiesen wird, wie der Teuffel keine Wunder thun könne, und also die Wunder der Aegyptischen Zauberer ... durch Gottes Macht geschehen. Am Ende sind beygefüget M. Pascals Sonderbahre Gedancken von Wundern</title></titleOfWork><titleOfWork source="VIAF" subsource="SUDOC"><title>The @works of William Fleetwood</title></titleOfWork><titleOfWork source="NTA"><title>@Four sermons I. On the death of Queen Mary, 1694. II. On the death of the Duke of Gloucester, 1700. III. On the death of King William, 1701. IV. On the Queen's accession to the throne, in 1703. By William Lord Bishop of St. Asaph.</title></titleOfWork><titleOfWork source="NTA"><title>Les @reports des cases en les ans des roys Edward V., Richard III., Henrie VII., et Henrie VIII.</title><subtitle>Touts qui par cy devant ont este publies</subtitle><subtitle>or nouvellement impr., corr. et revieue: oue plusieurs bonnes notes ...; qui referrent les cases al'abbregement de Brook, et autres livres des ans ...</subtitle></titleOfWork><titleOfWork source="NTA"><title>A @sermon on the fast-day, January the sixteenth, 1711/12 against such as delight in war. By a divine of the Church of England.</title></titleOfWork><titleOfWork source="NTA"><title>@Sermon preach'd August the 4th 1700</title></titleOfWork><titleOfWork source="NTA"><title>@vier voortreffelyke predikatien</title></titleOfWork><titleOfWork source="NTA"><title>The @works of William Fleetwood</title></titleOfWork><titleOfWork source="BNF"><title>@Chronicon preciosum:  or, an Account of English money. The price of corn, and other commodities, for the last 600 years. In a letter to a student in the university of Oxford</title></titleOfWork><titleOfWork source="BNF"><title>@Defence of praying before sermon, as directed by the LVth canon</title></titleOfWork><titleOfWork source="BNF"><title>The @reasonable communicant or, an explanation of the doctrine of the sacrament of the Lord's Supper, in all its parts, from the communion service. In a discourse between a minister and one of his parishioners. By W. Fleetwood.</title></titleOfWork><identifier><identifierType>ISBN</identifierType><identifierValue>9789536093847</identifierValue><source>VIAF</source><source>NSK</source></identifier><identifier><identifierType>ISBN</identifierType><identifierValue>9780300075069</identifierValue><source>VIAF</source><source>NSK</source></identifier></creativeActivity><personalNameVariant><surname>Eminent divine lately deceased</surname><nameUse>public</nameUse><source>LCNACO</source></personalNameVariant><personalNameVariant><surname>Eminent divine lately deceased</surname><marcDate>1656-1723</marcDate><nameUse>public</nameUse><source>LCNACO</source></personalNameVariant><personalNameVariant><surname>Lay hand</surname><marcDate>1656-1723</marcDate><nameUse>public</nameUse><source>LCNACO</source></personalNameVariant><personalNameVariant><surname>William</surname><nameTitle>Lord Bishop of St. Asaph</nameTitle><marcDate>1656-1723</marcDate><nameUse>public</nameUse><source>LCNACO</source></personalNameVariant><personalNameVariant><forename>W</forename><surname>Fleetwood</surname><marcDate>1656-1723</marcDate><nameUse>public</nameUse><source>LCNACO</source></personalNameVariant><personalNameVariant><forename>William</forename><surname>Fleetwood</surname><nameTitle>bp. of Ely</nameTitle><marcDate>1656-1723</marcDate><nameUse>public</nameUse><source>LCNACO</source></personalNameVariant><personalNameVariant><surname>Doctor invicibilis</surname><source>VIAF</source><source>NSK</source></personalNameVariant><personalNameVariant><surname>Eminent divine lately deceased</surname><marcDate>1656-1723</marcDate><source>VIAF</source><source>N6I</source></personalNameVariant><personalNameVariant><forename>Guilelmus</forename><surname>Fleetwood</surname><marcDate>1656-1723</marcDate><source>VIAF</source><source>DNB</source></personalNameVariant><personalNameVariant><forename>W.</forename><surname>Fleetwood</surname><marcDate>1656-1723</marcDate><source>VIAF</source><source>NLI</source></personalNameVariant><personalNameVariant><forename>W.</forename><surname>Fleetwood</surname><marcDate>1656-1723</marcDate><source>VIAF</source><source>N6I</source></personalNameVariant><personalNameVariant><forename>William</forename><surname>Fleetwood</surname><nameTitle>bp. of Ely</nameTitle><marcDate>1656-1723</marcDate><source>VIAF</source><source>NLI</source></personalNameVariant><personalNameVariant><forename>William</forename><surname>Fleetwood</surname><nameTitle>bp. of Ely</nameTitle><marcDate>1656-1723</marcDate><source>VIAF</source><source>N6I</source></personalNameVariant><personalNameVariant><forename>Guilelmus</forename><surname>Fletwood</surname><marcDate>1656-1723</marcDate><source>VIAF</source><source>DNB</source></personalNameVariant><personalNameVariant><surname>Guglielmo d'Occam</surname><source>VIAF</source><source>NSK</source></personalNameVariant><personalNameVariant><surname>Guglielmo di Ockham</surname><source>VIAF</source><source>NSK</source></personalNameVariant><personalNameVariant><surname>Guilelmus de Occam</surname><source>VIAF</source><source>NSK</source></personalNameVariant><personalNameVariant><surname>Guillaume d'Occam</surname><source>VIAF</source><source>NSK</source></personalNameVariant><personalNameVariant><surname>Gulielmus Occhamus</surname><source>VIAF</source><source>NSK</source></personalNameVariant><personalNameVariant><surname>Lay hand</surname><marcDate>1656-1723</marcDate><source>VIAF</source><source>NLI</source></personalNameVariant><personalNameVariant><surname>Lay hand</surname><marcDate>1656-1723</marcDate><source>VIAF</source><source>N6I</source></personalNameVariant><personalNameVariant><surname>Occam</surname><source>VIAF</source><source>NSK</source></personalNameVariant><personalNameVariant><forename>William</forename><surname>Occam</surname><source>VIAF</source><source>NSK</source></personalNameVariant><personalNameVariant><surname>Ockham</surname><source>VIAF</source><source>NSK</source></personalNameVariant><personalNameVariant><forename>Vilim</forename><surname>Ockham</surname><source>VIAF</source><source>NSK</source></personalNameVariant><personalNameVariant><forename>Wilhelm von</forename><surname>Ockham</surname><source>VIAF</source><source>NSK</source></personalNameVariant><personalNameVariant><surname>Vilim Ockhamski</surname><source>VIAF</source><source>NSK</source></personalNameVariant><personalNameVariant><surname>Vilim iz Ockhama</surname><source>VIAF</source><source>NSK</source></personalNameVariant><personalNameVariant><forename>Wilhelm</forename><surname>Von Ockham</surname><source>VIAF</source><source>NSK</source></personalNameVariant><personalNameVariant><surname>Wilhelm Ockham</surname><source>VIAF</source><source>NSK</source></personalNameVariant><personalNameVariant><surname>William Fleetwood</surname><nameTitle>Anglican bishop</nameTitle><source>VIAF</source><source>WKP</source></personalNameVariant><personalNameVariant><surname>William Fleetwood‏</surname><nameTitle>vescovo anglicano</nameTitle><source>VIAF</source><source>WKP</source></personalNameVariant><personalNameVariant><surname>William Ockham</surname><source>VIAF</source><source>NSK</source></personalNameVariant><personalNameVariant><surname>William Ockhamski</surname><source>VIAF</source><source>NSK</source></personalNameVariant><personalNameVariant><surname>William iz Ockhama</surname><source>VIAF</source><source>NSK</source></personalNameVariant><personalNameVariant><surname>William of Occam</surname><source>VIAF</source><source>NSK</source></personalNameVariant><personalNameVariant><surname>William</surname><nameTitle>Lord Bishop of St. Asaph</nameTitle><marcDate>1656-1723</marcDate><source>VIAF</source><source>N6I</source></personalNameVariant><personalNameVariant><forename>a</forename><surname>Divine of the Church of England</surname><marcDate>1656-1723</marcDate><source>NTA</source></personalNameVariant><personalNameVariant><forename>William</forename><surname>Fleetwood</surname><nameTitle>Bishop of Ely</nameTitle><marcDate>1656-1723</marcDate><source>NTA</source></personalNameVariant><personalNameVariant><forename>Guilhelmus</forename><surname>Fletewoodus</surname><marcDate>1656-1723</marcDate><source>NTA</source></personalNameVariant><personalNameVariant><surname>William</surname><nameTitle>Bishop of St. Asaph</nameTitle><marcDate>1656-1723</marcDate><source>NTA</source></personalNameVariant><otherIdentifierOfIdentity><type>OCoLC</type><identifier>oca00880565</identifier><source>LCNACO</source></otherIdentifierOfIdentity><sources><codeOfSource>VIAF</codeOfSource><sourceIdentifier>49248091</sourceIdentifier><reference><class>ALL</class><role>CRE</role><URI>http://viaf.org/viaf/49248091</URI></reference></sources><sources><codeOfSource>BNF</codeOfSource><sourceIdentifier>12069721</sourceIdentifier></sources><sources><codeOfSource>NTA</codeOfSource><sourceIdentifier>068156855</sourceIdentifier></sources><sources><codeOfSource>LCNACO</codeOfSource><sourceIdentifier>n  82225806</sourceIdentifier></sources><externalInformation><information>Wikipedia</information><URI>https://en.wikipedia.org/wiki/William_Fleetwood</URI></externalInformation></ISNIAssigned>