<ISNIAssigned><isniUnformatted>000000011493542X</isniUnformatted><isniURI>https://isni.org/isni/000000011493542X</isniURI><dataConfidence>60</dataConfidence><personalName><surname>Alan King-Hamilton</surname><nameUse>public</nameUse><source>VIAF</source><source>WKP</source><subsourceIdentifier>Q4707059</subsourceIdentifier></personalName><personalName><forename>Alan</forename><surname>King-Hamilton</surname><marcDate>1904-</marcDate><nameUse>public</nameUse><source>VIAF</source><source>DNB</source><subsourceIdentifier>134014677</subsourceIdentifier></personalName><personalName><forename>Alan</forename><surname>King-Hamilton</surname><marcDate>1904-2010</marcDate><nameUse>public</nameUse><source>LCNACO</source></personalName><personalName><forename>Alan</forename><surname>King-Hamilton</surname><marcDate>1904-2010</marcDate><nameUse>public</nameUse><source>NTA</source></personalName><creativeActivity><creationClass source="NTA">am</creationClass><titleOfWork source="LCNACO"><title>@And nothing but the truth</title></titleOfWork><titleOfWork source="LCNACO"><title>A @history of the first seventy-five years of the Avenue Lodge No. 3231, 1982:</title></titleOfWork><titleOfWork source="NTA"><title>@And nothing but the truth, 1982:</title></titleOfWork><identifier><identifierType>ISBN</identifierType><identifierValue>9780297780533</identifierValue><source>LCNACO</source></identifier><identifier><identifierType>ISBN</identifierType><identifierValue>9780297780533</identifierValue><source>NTA</source></identifier></creativeActivity><personalNameVariant><surname>Alan King-Hamilton</surname><nameTitle>British barrister and judge</nameTitle><source>VIAF</source><source>WKP</source></personalNameVariant><personalNameVariant><surname>Alan King-Hamilton</surname><nameTitle>Brits rechter (1904-2010)</nameTitle><source>VIAF</source><source>WKP</source></personalNameVariant><personalNameVariant><surname>Alan King-Hamilton</surname><nameTitle>britischer Anwalt und Richter</nameTitle><source>VIAF</source><source>WKP</source></personalNameVariant><personalNameVariant><forename>Alan King-</forename><surname>Hamilton</surname><marcDate>1904-2010</marcDate><source>LCNACO</source></personalNameVariant><personalNameVariant><forename>Alan King-</forename><surname>Hamilton</surname><marcDate>1904-</marcDate><source>VIAF</source><source>DNB</source></personalNameVariant><personalNameVariant><forename>M. A. B.</forename><surname>King-Hamilton</surname><marcDate>1904-2010</marcDate><source>LCNACO</source></personalNameVariant><personalNameVariant><forename>Myer Alan Barry</forename><surname>King-Hamilton</surname><marcDate>1904-2010</marcDate><source>LCNACO</source></personalNameVariant><sources><codeOfSource>VIAF</codeOfSource><sourceIdentifier>72751776</sourceIdentifier><reference><class>ALL</class><role>CRE</role><URI>http://viaf.org/viaf/72751776</URI></reference></sources><sources><codeOfSource>NTA</codeOfSource><sourceIdentifier>070061475</sourceIdentifier></sources><sources><codeOfSource>LCNACO</codeOfSource><sourceIdentifier>n  82207344</sourceIdentifier></sources><externalInformation><information>Wikipedia</information><URI>https://en.wikipedia.org/wiki/Alan_King-Hamilton</URI></externalInformation><externalInformation><information>Wikipedia</information><URI>https://no.wikipedia.org/wiki/Alan_King-Hamilton</URI></externalInformation></ISNIAssigned>