<ISNIAssigned><isniUnformatted>0000000502493344</isniUnformatted><isniURI>https://isni.org/isni/0000000502493344</isniURI><dataConfidence>60</dataConfidence><personalName><forename>Sara</forename><surname>Decker</surname><source>MUBZ</source></personalName><creativeActivity><creationRole source="MUBZ">prf</creationRole><creationClass source="MUBZ">jm</creationClass><contributedToOrPerformed source="MUBZ"><title>@Baby One More Time</title></contributedToOrPerformed><contributedToOrPerformed source="MUBZ"><title>Der @schwere Traum</title></contributedToOrPerformed><contributedToOrPerformed source="MUBZ"><title>@Freedom of Flight</title></contributedToOrPerformed><contributedToOrPerformed source="MUBZ"><title>@Have You Got a Brook in Your Little Heart</title></contributedToOrPerformed><contributedToOrPerformed source="MUBZ"><title>@Kein Kinderlied</title></contributedToOrPerformed><contributedToOrPerformed source="MUBZ"><title>@Singing Lessons</title></contributedToOrPerformed><contributedToOrPerformed source="MUBZ"><title>The @Realm of You</title></contributedToOrPerformed><contributedToOrPerformed source="MUBZ"><title>@Time After Time</title></contributedToOrPerformed><contributedToOrPerformed source="MUBZ"><title>@You Cover Yourself</title></contributedToOrPerformed></creativeActivity><personalNameVariant><surname>Sara Decker</surname><source>MUBZ</source></personalNameVariant><sources><codeOfSource>MUBZ</codeOfSource><sourceIdentifier>30770203-1725-41a9-8cf8-f6d884eaf9b4</sourceIdentifier></sources><externalInformation><URI>http://www.saradeckermusic.com/</URI></externalInformation><externalInformation><URI>https://de.wikipedia.org/wiki/Sara_Decker</URI></externalInformation></ISNIAssigned>