<ISNIAssigned><isniUnformatted>0000000494567250</isniUnformatted><isniURI>https://isni.org/isni/0000000494567250</isniURI><dataConfidence>60</dataConfidence><organisation><organisationName><mainName>Conley Harris and Howard Truelove Collection (Philadelphia, Pa.)</mainName><source>LCNACO</source></organisationName><usageDateFrom>2013</usageDateFrom><creativeActivity><creationRole source="LCNACO">aut</creationRole><creationClass source="LCNACO">am</creationClass><titleOfWork source="LCNACO"><title>@Drawn from courtly India</title></titleOfWork></creativeActivity><organisationNameVariant><mainName>Philadelphia Museum of Art</mainName><subdivisionName>Conley Harris and Howard Truelove Collection</subdivisionName></organisationNameVariant><isRelatedOrganisation><mainName>Philadelphia Museum of Art</mainName><relationshipType>isAffiliatedWith</relationshipType></isRelatedOrganisation></organisation><otherIdentifierOfIdentity><type>OCoLC</type><identifier>oca10419993</identifier><source>LCNACO</source></otherIdentifierOfIdentity><sources><codeOfSource>LCNACO</codeOfSource><sourceIdentifier>no2016036932</sourceIdentifier></sources><externalInformation><information>(Drawn from Courtly India: The Conley Harris and Howard Truelove Collection ... Drawings reveal what paintings conceal, and the works in this exhibition offer new ways of looking and thinking about the art of Indian drawing)</information><URI>http://www.philamuseum.org/exhibitions/828.html</URI></externalInformation></ISNIAssigned>