<ISNIAssigned><isniUnformatted>0000000499424080</isniUnformatted><isniURI>https://isni.org/isni/0000000499424080</isniURI><dataConfidence>60</dataConfidence><personalName><forename>M</forename><surname>Schachter</surname><marcDate>1920-2000</marcDate><nameUse>public</nameUse><source>LCNACO</source></personalName><creativeActivity><creationRole source="LCNACO">aut</creationRole><creationClass source="LCNACO">am</creationClass><titleOfWork source="LCNACO"><title>@Experimental studies on motion sickness</title></titleOfWork></creativeActivity><personalNameVariant><forename>Melville</forename><surname>Schachter</surname><marcDate>1920-2000</marcDate><nameUse>public</nameUse><source>LCNACO</source></personalNameVariant><otherIdentifierOfIdentity><type>OCoLC</type><identifier>oca11458546</identifier><source>LCNACO</source></otherIdentifierOfIdentity><sources><codeOfSource>LCNACO</codeOfSource><sourceIdentifier>no2018097015</sourceIdentifier></sources><externalInformation><information>pages 12-13 (Professor Melville Schachter, MSc MD CM (1920-2000); died in London on May 18; graduate of McGill University; assistant professor in the Department of Physiology at Dalhousie University; joined the National Institute of Medical Research at Mill Hill, London in 1950; in 1954 joined University College, London as Lecturer and later Reader in Physiology; returned to Canada in 1965 to become Professor and Head of the Department of Physiology at the University of Alberta, retiring in 1986)</information><URI>http://edition.pagesuite-professional.co.uk/launch.aspx?eid=41386840-f73f-4faa-b005-e0dee45bcd59&#38;pnum=16</URI></externalInformation><externalInformation><information>title page (Melville Schachter, B.Sc.; McGill University)</information><URI>http://digitool.Library.McGill.CA/R/?func=dbin-jump-full&#38;object_id=125744</URI></externalInformation></ISNIAssigned>